Workbook

Sheet Dashboard
B2: Painel de Pessoas | Y2: FECHAMENTO DA FOLHA
B3: RH · headcount, movimentação, turnover, perfil e remuneração | Y3: =Calc!B7
B5: DEPTO | D5: Todos | G5: UNIDADE | I5: Todas | L5: ANO | N5: 2026 | Q5: ◀ Ano vale para admissões, desligamentos e turnover. Headcount é a foto do fechamento.
B7: HEADCOUNT ATIVO | G7: ADMISSÕES | L7: DESLIGAMENTOS | Q7: TURNOVER | V7: SALÁRIO MÉDIO | AA7: MULHERES
B8: =Calc!B13 | G8: =Calc!B14 | L8: =Calc!B16 | Q8: =Calc!B18 | V8: =Calc!B19 | AA8: =Calc!B21
B10: =Calc!B23 | G10: =Calc!B24 | L10: =Calc!B25 | Q10: ="(adm. + desl.) ÷ 2 ÷ ativos" | V10: =Calc!B20 | AA10: =Calc!B22
B12: Pessoas por departamento | M12: Admissões × desligamentos por mês
B13: ativos no fechamento | M13: ano escolhido · quando a barra laranja passa a azul, o time está encolhendo
B29: Pirâmide etária | P29: Por que as pessoas saem | Y29: Gênero
B30: ativos por faixa de idade · mulheres à direita, homens à esquerda | P30: desligamentos no ano por motivo | Y30: ativos
B46: Quadro por departamento
B47: barra = salário médio · cor da avaliação: vermelho (baixa) → verde (alta)
B48: DEPARTAMENTO | G48: ATIVOS | I48: % MULHERES | L48: SALÁRIO MÉDIO | R48: TEMPO DE CASA | U48: AVALIAÇÃO | X48: ADMISSÕES | AA48: DESLIGAMENTOS
B49: =Calc!A74 | G49: =Calc!B74 | I49: =Calc!C74 | L49: =Calc!D74 | R49: =Calc!E74 | U49: =Calc!F74 | X49: =Calc!G74 | AA49: =Calc!H74
B50: =Calc!A75 | G50: =Calc!B75 | I50: =Calc!C75 | L50: =Calc!D75 | R50: =Calc!E75 | U50: =Calc!F75 | X50: =Calc!G75 | AA50: =Calc!H75
B51: =Calc!A76 | G51: =Calc!B76 | I51: =Calc!C76 | L51: =Calc!D76 | R51: =Calc!E76 | U51: =Calc!F76 | X51: =Calc!G76 | AA51: =Calc!H76
B52: =Calc!A77 | G52: =Calc!B77 | I52: =Calc!C77 | L52: =Calc!D77 | R52: =Calc!E77 | U52: =Calc!F77 | X52: =Calc!G77 | AA52: =Calc!H77
B53: =Calc!A78 | G53: =Calc!B78 | I53: =Calc!C78 | L53: =Calc!D78 | R53: =Calc!E78 | U53: =Calc!F78 | X53: =Calc!G78 | AA53: =Calc!H78
B54: =Calc!A79 | G54: =Calc!B79 | I54: =Calc!C79 | L54: =Calc!D79 | R54: =Calc!E79 | U54: =Calc!F79 | X54: =Calc!G79 | AA54: =Calc!H79
B55: =Calc!A80 | G55: =Calc!B80 | I55: =Calc!C80 | L55: =Calc!D80 | R55: =Calc!E80 | U55: =Calc!F80 | X55: =Calc!G80 | AA55: =Calc!H80
B59: Dados fictícios para estudo. Turnover = ((admissões + desligamentos) ÷ 2) ÷ headcount ativo, no período. A pirâmide etária usa um truque: os homens entram com sinal negativo e o formato de número esconde o sinal.

Sheet Passo a passo
B2: Passo a passo · Painel de Pessoas
B3: Siga as etapas na ordem. Cada linha diz onde clicar, o que fazer, a fórmula e o porquê.
B5: ETAPA 1 · Base de funcionários
B6: Uma linha por pessoa. Datas de admissão e desligamento são a matéria-prima de quase todos os indicadores de RH.
B7: Passo | C7: Onde | D7: O que fazer | E7: Fórmula / recurso | F7: Por que assim
B8: 1 | C8: Funcionarios | D8: Transforme em Tabela (tbFuncionarios). | E8: Ctrl + Alt + T | F8: Contratou alguém? Nova linha, painel atualizado.
B9: 2 | C9: Funcionarios › Idade | D9: Idade na data de referência (ou no desligamento). | E9: =DATADIF(D2;SE(K2="";Calc!$B$7;K2);"a") | F9: DATADIF com "a" conta anos completos. Ela não aparece no assistente, mas funciona.
B10: 3 | C10: Funcionarios › Faixa etária | D10: Agrupe idades em faixas. | E10: =PROC(E2;{0;25;35;45;55};{"18-24";"25-34";"35-44";"45-54";"55+"}) | F10: PROC aproximado acha a faixa certa: 31 cai em 25-34.
B11: 4 | C11: Funcionarios › Status | D11: Ativo se não tem data de desligamento. | E11: =SE(K2="";"Ativo";"Desligado") | F11: Headcount = contar 'Ativo'.
B12: 5 | C12: Funcionarios › Tempo de casa | D12: Anos entre admissão e hoje (ou desligamento). | E12: =ARRED((SE(K2="";ref;K2)-J2)/365,25;1) | F12: Datas são números: subtrair dá dias; ÷365,25 dá anos.
B13: 6 | C13: Funcionarios › Liderança | D13: Marca quem é Coordenação, Gerência ou Diretoria. | E13: =SE(OU(H2="Coordenação";H2="Gerência";H2="Diretoria");"Sim";"Não") | F13: Permite medir diversidade na liderança.
B15: ETAPA 2 · Os KPIs de RH
B16: Passo | C16: Onde | D16: O que fazer | E16: Fórmula / recurso | F16: Por que assim
B17: 7 | C17: Calc › B13 | D17: Headcount ativo com filtros. | E17: =CONT.SES(Status;"Ativo";Depto;critério;Unidade;critério) | F17: Foto do fechamento: quantas pessoas estão na casa hoje.
B18: 8 | C18: Calc › B14 e B16 | D18: Admissões e desligamentos no ano. | E18: =CONT.SES(Admissão;">="&início;Admissão;"<="&fim;…) | F18: Movimento é sempre num período: precisa de data inicial e final.
B19: 9 | C19: Calc › B18 | D19: Turnover. | E19: =SEERRO(((B14+B16)/2)/B13;0) | F19: Fórmula de mercado: média entre entradas e saídas sobre o quadro. Acima de ~15% ao ano acende alerta.
B20: 10 | C20: Calc › B19 e B20 | D20: Salário médio e folha. | E20: =MÉDIASES(Salário;Status;"Ativo";…) · =SOMASES(…) | F20: Média mostra o 'típico'; folha mostra o custo total.
B21: 11 | C21: Calc › B21 e B22 | D21: Diversidade: % mulheres e % mulheres na liderança. | E21: =CONT.SES(…;Gênero;"F";Liderança;"Sim")/CONT.SES(…;Liderança;"Sim") | F21: Os dois juntos contam a história: equilíbrio geral × no topo.
B23: ETAPA 3 · Pirâmide etária (truque de especialista)
B24: Não existe 'gráfico de pirâmide' no Excel. Ele é um gráfico de barras com um detalhe esperto.
B25: Passo | C25: Onde | D25: O que fazer | E25: Fórmula / recurso | F25: Por que assim
B26: 12 | C26: Calc › seção 5 | D26: Conte mulheres por faixa (positivo) e homens por faixa com sinal NEGATIVO. | E26: =-CONT.SES(…;Gênero;"M") | F26: Valor negativo faz a barra crescer para a esquerda.
B27: 13 | C27: Inserir | D27: Gráfico de Barras Agrupadas com as duas séries. | E27: Inserir › Barras › Barra Agrupada | F27: Uma série para cada lado.
B28: 14 | C28: Formatar Série | D28: Sobreposição 100% e largura do espaçamento 25%. | E28: Formatar Série › Sobreposição: 100% | F28: As duas barras ficam na mesma linha, uma de cada lado do zero.
B29: 15 | C29: Formatar Eixo e rótulos | D29: Formato de número que esconde o sinal de menos. | E29: Formato: #.##0;#.##0 | F29: A segunda parte do formato (negativos) é escrita sem o '-'. O gráfico mostra 12, não −12.
B30: 16 | C30: Eixo vertical | D30: Rótulos do eixo em 'Baixo'. | E30: Formatar Eixo › Rótulos › Posição: Baixo | F30: Tira os nomes das faixas do meio da pirâmide.
B32: ETAPA 4 · Demais visuais
B33: Passo | C33: Onde | D33: O que fazer | E33: Fórmula / recurso | F33: Por que assim
B34: 17 | C34: Pessoas por departamento | D34: Barras horizontais da tabela ordenada (MAIOR + ÍNDICE/CORRESP). | E34: Formatar Eixo › Categorias em ordem inversa | F34: Ranking lido de cima para baixo.
B35: 18 | C35: Admissões × desligamentos | D35: Colunas agrupadas: azul = entra, laranja = sai. | E35: Inserir › Coluna Agrupada | F35: Mês a mês dá para ver se o time cresce ou encolhe.
B36: 19 | C36: Gênero | D36: Rosca com 2 fatias e rótulos em %. | E36: Inserir › Rosca | F36: Rosca é ótima para 2 a 4 partes de um todo.
B37: 20 | C37: Quadro por departamento | D37: Barras de dados no salário e escala de cores na avaliação. | E37: Formatação Condicional › Escalas de Cor › Mais Regras (mín 3,2 · ponto médio 3,8 · máx 4,4) | F37: Limites fixos: a cor tem o mesmo significado em qualquer filtro.
B39: ETAPA 5 · Desafios para virar especialista
B40: Passo | C40: Onde | D40: O que fazer | E40: Fórmula / recurso | F40: Por que assim
B41: 21 | C41: Desafio 1 | D41: Crie o KPI 'Absenteísmo' com uma nova tabela de faltas. | E41: Nova Tabela + SOMASES | F41: Painel de RH real cruza várias bases.
B42: 22 | C42: Desafio 2 | D42: Adicione 'Tempo médio até o desligamento' de quem saiu no ano. | E42: MÉDIASES(Tempo de casa;Status;"Desligado";…) | F42: Mostra se as pessoas saem cedo (problema de integração) ou tarde.
B43: 23 | C43: Desafio 3 | D43: Faça uma matriz Nível × Gênero com salário médio e destaque diferenças acima de 5%. | E43: MÉDIASES com dois critérios + formatação condicional | F43: Equidade salarial é tema quente em qualquer empresa.

Sheet Calc
A1: 1 · FILTROS E DATAS
A3: Departamento escolhido | B3: =Dashboard!$D$5
A4: Unidade escolhida | B4: =Dashboard!$I$5
A5: Ano dos movimentos | B5: =Dashboard!$N$5
A6: Critério depto · unidade | B6: =IF($B$3="Todos","*",$B$3) | C6: =IF($B$4="Todas","*",$B$4)
A7: Data de referência (fechamento) | B7: 46295 | C7: premissa: data do último fechamento da folha
A8: Início do ano | B8: =DATE($B$5,1,1)
A9: Fim efetivo do ano | B9: =MIN(DATE($B$5,12,31),$B$7)
A10: Mesmo período ano anterior (fim) | B10: =EDATE($B$9,-12)
A12: 2 · KPIs
A13: Headcount ativo | B13: =COUNTIFS(Funcionarios!$O$2:$O$176,"Ativo",Funcionarios!$G$2:$G$176,$B$6,Funcionarios!$M$2:$M$176,$C$6)
A14: Admissões no ano | B14: =COUNTIFS(Funcionarios!$J$2:$J$176,">="&$B$8,Funcionarios!$J$2:$J$176,"<="&$B$9,Funcionarios!$G$2:$G$176,$B$6,Funcionarios!$M$2:$M$176,$C$6)
A15: Admissões mesmo período ano anterior | B15: =COUNTIFS(Funcionarios!$J$2:$J$176,">="&EDATE($B$8,-12),Funcionarios!$J$2:$J$176,"<="&$B$10,Funcionarios!$G$2:$G$176,$B$6,Funcionarios!$M$2:$M$176,$C$6)
A16: Desligamentos no ano | B16: =COUNTIFS(Funcionarios!$K$2:$K$176,">="&$B$8,Funcionarios!$K$2:$K$176,"<="&$B$9,Funcionarios!$G$2:$G$176,$B$6,Funcionarios!$M$2:$M$176,$C$6)
A17: Desligamentos mesmo período ano anterior | B17: =COUNTIFS(Funcionarios!$K$2:$K$176,">="&EDATE($B$8,-12),Funcionarios!$K$2:$K$176,"<="&$B$10,Funcionarios!$G$2:$G$176,$B$6,Funcionarios!$M$2:$M$176,$C$6)
A18: Turnover do período | B18: =IFERROR(((B14+B16)/2)/B13,0)
A19: Salário médio (ativos) | B19: =IFERROR(AVERAGEIFS(Funcionarios!$I$2:$I$176,Funcionarios!$O$2:$O$176,"Ativo",Funcionarios!$G$2:$G$176,$B$6,Funcionarios!$M$2:$M$176,$C$6),0)
A20: Folha mensal (ativos) | B20: =SUMIFS(Funcionarios!$I$2:$I$176,Funcionarios!$O$2:$O$176,"Ativo",Funcionarios!$G$2:$G$176,$B$6,Funcionarios!$M$2:$M$176,$C$6)
A21: % mulheres (ativos) | B21: =IFERROR(COUNTIFS(Funcionarios!$O$2:$O$176,"Ativo",Funcionarios!$G$2:$G$176,$B$6,Funcionarios!$M$2:$M$176,$C$6,Funcionarios!$C$2:$C$176,"F")/B13,0)
A22: % mulheres na liderança | B22: =IFERROR(COUNTIFS(Funcionarios!$O$2:$O$176,"Ativo",Funcionarios!$G$2:$G$176,$B$6,Funcionarios!$M$2:$M$176,$C$6,Funcionarios!$C$2:$C$176,"F",Funcionarios!$Q$2:$Q$176,"Sim")/COUNTIFS(Funcionarios!$O$2:$O$176,"Ativo",Funcionarios!$G$2:$G$176,$B$6,Funcionarios!$M$2:$M$176,$C$6,Funcionarios!$Q$2:$Q$176,"Sim"),0)
A23: Tempo médio de casa (anos) | B23: =IFERROR(AVERAGEIFS(Funcionarios!$P$2:$P$176,Funcionarios!$O$2:$O$176,"Ativo",Funcionarios!$G$2:$G$176,$B$6,Funcionarios!$M$2:$M$176,$C$6),0)
A24: Variação admissões | B24: =IF(B15>0,B14/B15-1,"")
A25: Variação desligamentos | B25: =IF(B17>0,B16/B17-1,"")
A27: 3 · HEADCOUNT POR DEPARTAMENTO (ordenado) | C27: filtro de unidade aplicado
A28: Departamento | B28: Ativos | C28: Desempate | E28: Ordem | F28: Depto (ordenado) | G28: Ativos
A29: Comercial | B29: =COUNTIFS(Funcionarios!$O$2:$O$176,"Ativo",Funcionarios!$G$2:$G$176,A29,Funcionarios!$M$2:$M$176,$C$6) | C29: =B29+ROW()/1000000 | E29: 1 | F29: =INDEX($A$29:$A$35,MATCH(LARGE($C$29:$C$35,E29),$C$29:$C$35,0)) | G29: =INDEX($B$29:$B$35,MATCH(LARGE($C$29:$C$35,E29),$C$29:$C$35,0))
A30: Operações | B30: =COUNTIFS(Funcionarios!$O$2:$O$176,"Ativo",Funcionarios!$G$2:$G$176,A30,Funcionarios!$M$2:$M$176,$C$6) | C30: =B30+ROW()/1000000 | E30: 2 | F30: =INDEX($A$29:$A$35,MATCH(LARGE($C$29:$C$35,E30),$C$29:$C$35,0)) | G30: =INDEX($B$29:$B$35,MATCH(LARGE($C$29:$C$35,E30),$C$29:$C$35,0))
A31: Tecnologia | B31: =COUNTIFS(Funcionarios!$O$2:$O$176,"Ativo",Funcionarios!$G$2:$G$176,A31,Funcionarios!$M$2:$M$176,$C$6) | C31: =B31+ROW()/1000000 | E31: 3 | F31: =INDEX($A$29:$A$35,MATCH(LARGE($C$29:$C$35,E31),$C$29:$C$35,0)) | G31: =INDEX($B$29:$B$35,MATCH(LARGE($C$29:$C$35,E31),$C$29:$C$35,0))
A32: Financeiro | B32: =COUNTIFS(Funcionarios!$O$2:$O$176,"Ativo",Funcionarios!$G$2:$G$176,A32,Funcionarios!$M$2:$M$176,$C$6) | C32: =B32+ROW()/1000000 | E32: 4 | F32: =INDEX($A$29:$A$35,MATCH(LARGE($C$29:$C$35,E32),$C$29:$C$35,0)) | G32: =INDEX($B$29:$B$35,MATCH(LARGE($C$29:$C$35,E32),$C$29:$C$35,0))
A33: Marketing | B33: =COUNTIFS(Funcionarios!$O$2:$O$176,"Ativo",Funcionarios!$G$2:$G$176,A33,Funcionarios!$M$2:$M$176,$C$6) | C33: =B33+ROW()/1000000 | E33: 5 | F33: =INDEX($A$29:$A$35,MATCH(LARGE($C$29:$C$35,E33),$C$29:$C$35,0)) | G33: =INDEX($B$29:$B$35,MATCH(LARGE($C$29:$C$35,E33),$C$29:$C$35,0))
A34: RH | B34: =COUNTIFS(Funcionarios!$O$2:$O$176,"Ativo",Funcionarios!$G$2:$G$176,A34,Funcionarios!$M$2:$M$176,$C$6) | C34: =B34+ROW()/1000000 | E34: 6 | F34: =INDEX($A$29:$A$35,MATCH(LARGE($C$29:$C$35,E34),$C$29:$C$35,0)) | G34: =INDEX($B$29:$B$35,MATCH(LARGE($C$29:$C$35,E34),$C$29:$C$35,0))
A35: Diretoria | B35: =COUNTIFS(Funcionarios!$O$2:$O$176,"Ativo",Funcionarios!$G$2:$G$176,A35,Funcionarios!$M$2:$M$176,$C$6) | C35: =B35+ROW()/1000000 | E35: 7 | F35: =INDEX($A$29:$A$35,MATCH(LARGE($C$29:$C$35,E35),$C$29:$C$35,0)) | G35: =INDEX($B$29:$B$35,MATCH(LARGE($C$29:$C$35,E35),$C$29:$C$35,0))
A37: 4 · ADMISSÕES × DESLIGAMENTOS POR MÊS | C37: ano escolhido
A38: Mês | B38: Admissões | C38: Desligamentos
A39: Jan | B39: =COUNTIFS(Funcionarios!$J$2:$J$176,">="&DATE($B$5,1,1),Funcionarios!$J$2:$J$176,"<="&EOMONTH(DATE($B$5,1,1),0),Funcionarios!$G$2:$G$176,$B$6,Funcionarios!$M$2:$M$176,$C$6) | C39: =COUNTIFS(Funcionarios!$K$2:$K$176,">="&DATE($B$5,1,1),Funcionarios!$K$2:$K$176,"<="&EOMONTH(DATE($B$5,1,1),0),Funcionarios!$G$2:$G$176,$B$6,Funcionarios!$M$2:$M$176,$C$6)
A40: Fev | B40: =COUNTIFS(Funcionarios!$J$2:$J$176,">="&DATE($B$5,2,1),Funcionarios!$J$2:$J$176,"<="&EOMONTH(DATE($B$5,2,1),0),Funcionarios!$G$2:$G$176,$B$6,Funcionarios!$M$2:$M$176,$C$6) | C40: =COUNTIFS(Funcionarios!$K$2:$K$176,">="&DATE($B$5,2,1),Funcionarios!$K$2:$K$176,"<="&EOMONTH(DATE($B$5,2,1),0),Funcionarios!$G$2:$G$176,$B$6,Funcionarios!$M$2:$M$176,$C$6)
A41: Mar | B41: =COUNTIFS(Funcionarios!$J$2:$J$176,">="&DATE($B$5,3,1),Funcionarios!$J$2:$J$176,"<="&EOMONTH(DATE($B$5,3,1),0),Funcionarios!$G$2:$G$176,$B$6,Funcionarios!$M$2:$M$176,$C$6) | C41: =COUNTIFS(Funcionarios!$K$2:$K$176,">="&DATE($B$5,3,1),Funcionarios!$K$2:$K$176,"<="&EOMONTH(DATE($B$5,3,1),0),Funcionarios!$G$2:$G$176,$B$6,Funcionarios!$M$2:$M$176,$C$6)
A42: Abr | B42: =COUNTIFS(Funcionarios!$J$2:$J$176,">="&DATE($B$5,4,1),Funcionarios!$J$2:$J$176,"<="&EOMONTH(DATE($B$5,4,1),0),Funcionarios!$G$2:$G$176,$B$6,Funcionarios!$M$2:$M$176,$C$6) | C42: =COUNTIFS(Funcionarios!$K$2:$K$176,">="&DATE($B$5,4,1),Funcionarios!$K$2:$K$176,"<="&EOMONTH(DATE($B$5,4,1),0),Funcionarios!$G$2:$G$176,$B$6,Funcionarios!$M$2:$M$176,$C$6)
A43: Mai | B43: =COUNTIFS(Funcionarios!$J$2:$J$176,">="&DATE($B$5,5,1),Funcionarios!$J$2:$J$176,"<="&EOMONTH(DATE($B$5,5,1),0),Funcionarios!$G$2:$G$176,$B$6,Funcionarios!$M$2:$M$176,$C$6) | C43: =COUNTIFS(Funcionarios!$K$2:$K$176,">="&DATE($B$5,5,1),Funcionarios!$K$2:$K$176,"<="&EOMONTH(DATE($B$5,5,1),0),Funcionarios!$G$2:$G$176,$B$6,Funcionarios!$M$2:$M$176,$C$6)
A44: Jun | B44: =COUNTIFS(Funcionarios!$J$2:$J$176,">="&DATE($B$5,6,1),Funcionarios!$J$2:$J$176,"<="&EOMONTH(DATE($B$5,6,1),0),Funcionarios!$G$2:$G$176,$B$6,Funcionarios!$M$2:$M$176,$C$6) | C44: =COUNTIFS(Funcionarios!$K$2:$K$176,">="&DATE($B$5,6,1),Funcionarios!$K$2:$K$176,"<="&EOMONTH(DATE($B$5,6,1),0),Funcionarios!$G$2:$G$176,$B$6,Funcionarios!$M$2:$M$176,$C$6)
A45: Jul | B45: =COUNTIFS(Funcionarios!$J$2:$J$176,">="&DATE($B$5,7,1),Funcionarios!$J$2:$J$176,"<="&EOMONTH(DATE($B$5,7,1),0),Funcionarios!$G$2:$G$176,$B$6,Funcionarios!$M$2:$M$176,$C$6) | C45: =COUNTIFS(Funcionarios!$K$2:$K$176,">="&DATE($B$5,7,1),Funcionarios!$K$2:$K$176,"<="&EOMONTH(DATE($B$5,7,1),0),Funcionarios!$G$2:$G$176,$B$6,Funcionarios!$M$2:$M$176,$C$6)
A46: Ago | B46: =COUNTIFS(Funcionarios!$J$2:$J$176,">="&DATE($B$5,8,1),Funcionarios!$J$2:$J$176,"<="&EOMONTH(DATE($B$5,8,1),0),Funcionarios!$G$2:$G$176,$B$6,Funcionarios!$M$2:$M$176,$C$6) | C46: =COUNTIFS(Funcionarios!$K$2:$K$176,">="&DATE($B$5,8,1),Funcionarios!$K$2:$K$176,"<="&EOMONTH(DATE($B$5,8,1),0),Funcionarios!$G$2:$G$176,$B$6,Funcionarios!$M$2:$M$176,$C$6)
A47: Set | B47: =COUNTIFS(Funcionarios!$J$2:$J$176,">="&DATE($B$5,9,1),Funcionarios!$J$2:$J$176,"<="&EOMONTH(DATE($B$5,9,1),0),Funcionarios!$G$2:$G$176,$B$6,Funcionarios!$M$2:$M$176,$C$6) | C47: =COUNTIFS(Funcionarios!$K$2:$K$176,">="&DATE($B$5,9,1),Funcionarios!$K$2:$K$176,"<="&EOMONTH(DATE($B$5,9,1),0),Funcionarios!$G$2:$G$176,$B$6,Funcionarios!$M$2:$M$176,$C$6)
A48: Out | B48: =COUNTIFS(Funcionarios!$J$2:$J$176,">="&DATE($B$5,10,1),Funcionarios!$J$2:$J$176,"<="&EOMONTH(DATE($B$5,10,1),0),Funcionarios!$G$2:$G$176,$B$6,Funcionarios!$M$2:$M$176,$C$6) | C48: =COUNTIFS(Funcionarios!$K$2:$K$176,">="&DATE($B$5,10,1),Funcionarios!$K$2:$K$176,"<="&EOMONTH(DATE($B$5,10,1),0),Funcionarios!$G$2:$G$176,$B$6,Funcionarios!$M$2:$M$176,$C$6)
A49: Nov | B49: =COUNTIFS(Funcionarios!$J$2:$J$176,">="&DATE($B$5,11,1),Funcionarios!$J$2:$J$176,"<="&EOMONTH(DATE($B$5,11,1),0),Funcionarios!$G$2:$G$176,$B$6,Funcionarios!$M$2:$M$176,$C$6) | C49: =COUNTIFS(Funcionarios!$K$2:$K$176,">="&DATE($B$5,11,1),Funcionarios!$K$2:$K$176,"<="&EOMONTH(DATE($B$5,11,1),0),Funcionarios!$G$2:$G$176,$B$6,Funcionarios!$M$2:$M$176,$C$6)
A50: Dez | B50: =COUNTIFS(Funcionarios!$J$2:$J$176,">="&DATE($B$5,12,1),Funcionarios!$J$2:$J$176,"<="&EOMONTH(DATE($B$5,12,1),0),Funcionarios!$G$2:$G$176,$B$6,Funcionarios!$M$2:$M$176,$C$6) | C50: =COUNTIFS(Funcionarios!$K$2:$K$176,">="&DATE($B$5,12,1),Funcionarios!$K$2:$K$176,"<="&EOMONTH(DATE($B$5,12,1),0),Funcionarios!$G$2:$G$176,$B$6,Funcionarios!$M$2:$M$176,$C$6)
A52: 5 · PIRÂMIDE ETÁRIA (ativos) | C52: a coluna Homens tem sinal NEGATIVO: é isso que desenha a pirâmide
A53: Faixa | B53: Mulheres | C53: Homens
A54: 18-24 | B54: =COUNTIFS(Funcionarios!$O$2:$O$176,"Ativo",Funcionarios!$G$2:$G$176,$B$6,Funcionarios!$M$2:$M$176,$C$6,Funcionarios!$F$2:$F$176,A54,Funcionarios!$C$2:$C$176,"F") | C54: =-COUNTIFS(Funcionarios!$O$2:$O$176,"Ativo",Funcionarios!$G$2:$G$176,$B$6,Funcionarios!$M$2:$M$176,$C$6,Funcionarios!$F$2:$F$176,A54,Funcionarios!$C$2:$C$176,"M")
A55: 25-34 | B55: =COUNTIFS(Funcionarios!$O$2:$O$176,"Ativo",Funcionarios!$G$2:$G$176,$B$6,Funcionarios!$M$2:$M$176,$C$6,Funcionarios!$F$2:$F$176,A55,Funcionarios!$C$2:$C$176,"F") | C55: =-COUNTIFS(Funcionarios!$O$2:$O$176,"Ativo",Funcionarios!$G$2:$G$176,$B$6,Funcionarios!$M$2:$M$176,$C$6,Funcionarios!$F$2:$F$176,A55,Funcionarios!$C$2:$C$176,"M")
A56: 35-44 | B56: =COUNTIFS(Funcionarios!$O$2:$O$176,"Ativo",Funcionarios!$G$2:$G$176,$B$6,Funcionarios!$M$2:$M$176,$C$6,Funcionarios!$F$2:$F$176,A56,Funcionarios!$C$2:$C$176,"F") | C56: =-COUNTIFS(Funcionarios!$O$2:$O$176,"Ativo",Funcionarios!$G$2:$G$176,$B$6,Funcionarios!$M$2:$M$176,$C$6,Funcionarios!$F$2:$F$176,A56,Funcionarios!$C$2:$C$176,"M")
A57: 45-54 | B57: =COUNTIFS(Funcionarios!$O$2:$O$176,"Ativo",Funcionarios!$G$2:$G$176,$B$6,Funcionarios!$M$2:$M$176,$C$6,Funcionarios!$F$2:$F$176,A57,Funcionarios!$C$2:$C$176,"F") | C57: =-COUNTIFS(Funcionarios!$O$2:$O$176,"Ativo",Funcionarios!$G$2:$G$176,$B$6,Funcionarios!$M$2:$M$176,$C$6,Funcionarios!$F$2:$F$176,A57,Funcionarios!$C$2:$C$176,"M")
A58: 55+ | B58: =COUNTIFS(Funcionarios!$O$2:$O$176,"Ativo",Funcionarios!$G$2:$G$176,$B$6,Funcionarios!$M$2:$M$176,$C$6,Funcionarios!$F$2:$F$176,A58,Funcionarios!$C$2:$C$176,"F") | C58: =-COUNTIFS(Funcionarios!$O$2:$O$176,"Ativo",Funcionarios!$G$2:$G$176,$B$6,Funcionarios!$M$2:$M$176,$C$6,Funcionarios!$F$2:$F$176,A58,Funcionarios!$C$2:$C$176,"M")
A60: 6 · MOTIVOS DE DESLIGAMENTO (ano escolhido)
A61: Motivo | B61: Desligamentos
A62: Pedido de demissão | B62: =COUNTIFS(Funcionarios!$L$2:$L$176,A62,Funcionarios!$K$2:$K$176,">="&$B$8,Funcionarios!$K$2:$K$176,"<="&$B$9,Funcionarios!$G$2:$G$176,$B$6,Funcionarios!$M$2:$M$176,$C$6)
A63: Dispensa | B63: =COUNTIFS(Funcionarios!$L$2:$L$176,A63,Funcionarios!$K$2:$K$176,">="&$B$8,Funcionarios!$K$2:$K$176,"<="&$B$9,Funcionarios!$G$2:$G$176,$B$6,Funcionarios!$M$2:$M$176,$C$6)
A64: Fim de contrato | B64: =COUNTIFS(Funcionarios!$L$2:$L$176,A64,Funcionarios!$K$2:$K$176,">="&$B$8,Funcionarios!$K$2:$K$176,"<="&$B$9,Funcionarios!$G$2:$G$176,$B$6,Funcionarios!$M$2:$M$176,$C$6)
A65: Aposentadoria | B65: =COUNTIFS(Funcionarios!$L$2:$L$176,A65,Funcionarios!$K$2:$K$176,">="&$B$8,Funcionarios!$K$2:$K$176,"<="&$B$9,Funcionarios!$G$2:$G$176,$B$6,Funcionarios!$M$2:$M$176,$C$6)
A67: 7 · GÊNERO (ativos)
A68: Gênero | B68: Ativos
A69: Mulheres | B69: =COUNTIFS(Funcionarios!$O$2:$O$176,"Ativo",Funcionarios!$G$2:$G$176,$B$6,Funcionarios!$M$2:$M$176,$C$6,Funcionarios!$C$2:$C$176,"F")
A70: Homens | B70: =COUNTIFS(Funcionarios!$O$2:$O$176,"Ativo",Funcionarios!$G$2:$G$176,$B$6,Funcionarios!$M$2:$M$176,$C$6,Funcionarios!$C$2:$C$176,"M")
A72: 8 · QUADRO POR DEPARTAMENTO | C72: filtro de unidade aplicado · todos os departamentos
A73: Departamento | B73: Ativos | C73: % mulheres | D73: Salário médio | E73: Tempo de casa | F73: Avaliação média | G73: Admissões no ano | H73: Deslig. no ano
A74: Comercial | B74: =COUNTIFS(Funcionarios!$O$2:$O$176,"Ativo",Funcionarios!$G$2:$G$176,A74,Funcionarios!$M$2:$M$176,$C$6) | C74: =IFERROR(COUNTIFS(Funcionarios!$O$2:$O$176,"Ativo",Funcionarios!$G$2:$G$176,A74,Funcionarios!$M$2:$M$176,$C$6,Funcionarios!$C$2:$C$176,"F")/B74,0) | D74: =IFERROR(AVERAGEIFS(Funcionarios!$I$2:$I$176,Funcionarios!$O$2:$O$176,"Ativo",Funcionarios!$G$2:$G$176,A74,Funcionarios!$M$2:$M$176,$C$6),0) | E74: =IFERROR(AVERAGEIFS(Funcionarios!$P$2:$P$176,Funcionarios!$O$2:$O$176,"Ativo",Funcionarios!$G$2:$G$176,A74,Funcionarios!$M$2:$M$176,$C$6),0) | F74: =IFERROR(AVERAGEIFS(Funcionarios!$N$2:$N$176,Funcionarios!$O$2:$O$176,"Ativo",Funcionarios!$G$2:$G$176,A74,Funcionarios!$M$2:$M$176,$C$6),0) | G74: =COUNTIFS(Funcionarios!$G$2:$G$176,A74,Funcionarios!$M$2:$M$176,$C$6,Funcionarios!$J$2:$J$176,">="&$B$8,Funcionarios!$J$2:$J$176,"<="&$B$9) | H74: =COUNTIFS(Funcionarios!$G$2:$G$176,A74,Funcionarios!$M$2:$M$176,$C$6,Funcionarios!$K$2:$K$176,">="&$B$8,Funcionarios!$K$2:$K$176,"<="&$B$9)
A75: Operações | B75: =COUNTIFS(Funcionarios!$O$2:$O$176,"Ativo",Funcionarios!$G$2:$G$176,A75,Funcionarios!$M$2:$M$176,$C$6) | C75: =IFERROR(COUNTIFS(Funcionarios!$O$2:$O$176,"Ativo",Funcionarios!$G$2:$G$176,A75,Funcionarios!$M$2:$M$176,$C$6,Funcionarios!$C$2:$C$176,"F")/B75,0) | D75: =IFERROR(AVERAGEIFS(Funcionarios!$I$2:$I$176,Funcionarios!$O$2:$O$176,"Ativo",Funcionarios!$G$2:$G$176,A75,Funcionarios!$M$2:$M$176,$C$6),0) | E75: =IFERROR(AVERAGEIFS(Funcionarios!$P$2:$P$176,Funcionarios!$O$2:$O$176,"Ativo",Funcionarios!$G$2:$G$176,A75,Funcionarios!$M$2:$M$176,$C$6),0) | F75: =IFERROR(AVERAGEIFS(Funcionarios!$N$2:$N$176,Funcionarios!$O$2:$O$176,"Ativo",Funcionarios!$G$2:$G$176,A75,Funcionarios!$M$2:$M$176,$C$6),0) | G75: =COUNTIFS(Funcionarios!$G$2:$G$176,A75,Funcionarios!$M$2:$M$176,$C$6,Funcionarios!$J$2:$J$176,">="&$B$8,Funcionarios!$J$2:$J$176,"<="&$B$9) | H75: =COUNTIFS(Funcionarios!$G$2:$G$176,A75,Funcionarios!$M$2:$M$176,$C$6,Funcionarios!$K$2:$K$176,">="&$B$8,Funcionarios!$K$2:$K$176,"<="&$B$9)
A76: Tecnologia | B76: =COUNTIFS(Funcionarios!$O$2:$O$176,"Ativo",Funcionarios!$G$2:$G$176,A76,Funcionarios!$M$2:$M$176,$C$6) | C76: =IFERROR(COUNTIFS(Funcionarios!$O$2:$O$176,"Ativo",Funcionarios!$G$2:$G$176,A76,Funcionarios!$M$2:$M$176,$C$6,Funcionarios!$C$2:$C$176,"F")/B76,0) | D76: =IFERROR(AVERAGEIFS(Funcionarios!$I$2:$I$176,Funcionarios!$O$2:$O$176,"Ativo",Funcionarios!$G$2:$G$176,A76,Funcionarios!$M$2:$M$176,$C$6),0) | E76: =IFERROR(AVERAGEIFS(Funcionarios!$P$2:$P$176,Funcionarios!$O$2:$O$176,"Ativo",Funcionarios!$G$2:$G$176,A76,Funcionarios!$M$2:$M$176,$C$6),0) | F76: =IFERROR(AVERAGEIFS(Funcionarios!$N$2:$N$176,Funcionarios!$O$2:$O$176,"Ativo",Funcionarios!$G$2:$G$176,A76,Funcionarios!$M$2:$M$176,$C$6),0) | G76: =COUNTIFS(Funcionarios!$G$2:$G$176,A76,Funcionarios!$M$2:$M$176,$C$6,Funcionarios!$J$2:$J$176,">="&$B$8,Funcionarios!$J$2:$J$176,"<="&$B$9) | H76: =COUNTIFS(Funcionarios!$G$2:$G$176,A76,Funcionarios!$M$2:$M$176,$C$6,Funcionarios!$K$2:$K$176,">="&$B$8,Funcionarios!$K$2:$K$176,"<="&$B$9)
A77: Financeiro | B77: =COUNTIFS(Funcionarios!$O$2:$O$176,"Ativo",Funcionarios!$G$2:$G$176,A77,Funcionarios!$M$2:$M$176,$C$6) | C77: =IFERROR(COUNTIFS(Funcionarios!$O$2:$O$176,"Ativo",Funcionarios!$G$2:$G$176,A77,Funcionarios!$M$2:$M$176,$C$6,Funcionarios!$C$2:$C$176,"F")/B77,0) | D77: =IFERROR(AVERAGEIFS(Funcionarios!$I$2:$I$176,Funcionarios!$O$2:$O$176,"Ativo",Funcionarios!$G$2:$G$176,A77,Funcionarios!$M$2:$M$176,$C$6),0) | E77: =IFERROR(AVERAGEIFS(Funcionarios!$P$2:$P$176,Funcionarios!$O$2:$O$176,"Ativo",Funcionarios!$G$2:$G$176,A77,Funcionarios!$M$2:$M$176,$C$6),0) | F77: =IFERROR(AVERAGEIFS(Funcionarios!$N$2:$N$176,Funcionarios!$O$2:$O$176,"Ativo",Funcionarios!$G$2:$G$176,A77,Funcionarios!$M$2:$M$176,$C$6),0) | G77: =COUNTIFS(Funcionarios!$G$2:$G$176,A77,Funcionarios!$M$2:$M$176,$C$6,Funcionarios!$J$2:$J$176,">="&$B$8,Funcionarios!$J$2:$J$176,"<="&$B$9) | H77: =COUNTIFS(Funcionarios!$G$2:$G$176,A77,Funcionarios!$M$2:$M$176,$C$6,Funcionarios!$K$2:$K$176,">="&$B$8,Funcionarios!$K$2:$K$176,"<="&$B$9)
A78: Marketing | B78: =COUNTIFS(Funcionarios!$O$2:$O$176,"Ativo",Funcionarios!$G$2:$G$176,A78,Funcionarios!$M$2:$M$176,$C$6) | C78: =IFERROR(COUNTIFS(Funcionarios!$O$2:$O$176,"Ativo",Funcionarios!$G$2:$G$176,A78,Funcionarios!$M$2:$M$176,$C$6,Funcionarios!$C$2:$C$176,"F")/B78,0) | D78: =IFERROR(AVERAGEIFS(Funcionarios!$I$2:$I$176,Funcionarios!$O$2:$O$176,"Ativo",Funcionarios!$G$2:$G$176,A78,Funcionarios!$M$2:$M$176,$C$6),0) | E78: =IFERROR(AVERAGEIFS(Funcionarios!$P$2:$P$176,Funcionarios!$O$2:$O$176,"Ativo",Funcionarios!$G$2:$G$176,A78,Funcionarios!$M$2:$M$176,$C$6),0) | F78: =IFERROR(AVERAGEIFS(Funcionarios!$N$2:$N$176,Funcionarios!$O$2:$O$176,"Ativo",Funcionarios!$G$2:$G$176,A78,Funcionarios!$M$2:$M$176,$C$6),0) | G78: =COUNTIFS(Funcionarios!$G$2:$G$176,A78,Funcionarios!$M$2:$M$176,$C$6,Funcionarios!$J$2:$J$176,">="&$B$8,Funcionarios!$J$2:$J$176,"<="&$B$9) | H78: =COUNTIFS(Funcionarios!$G$2:$G$176,A78,Funcionarios!$M$2:$M$176,$C$6,Funcionarios!$K$2:$K$176,">="&$B$8,Funcionarios!$K$2:$K$176,"<="&$B$9)
A79: RH | B79: =COUNTIFS(Funcionarios!$O$2:$O$176,"Ativo",Funcionarios!$G$2:$G$176,A79,Funcionarios!$M$2:$M$176,$C$6) | C79: =IFERROR(COUNTIFS(Funcionarios!$O$2:$O$176,"Ativo",Funcionarios!$G$2:$G$176,A79,Funcionarios!$M$2:$M$176,$C$6,Funcionarios!$C$2:$C$176,"F")/B79,0) | D79: =IFERROR(AVERAGEIFS(Funcionarios!$I$2:$I$176,Funcionarios!$O$2:$O$176,"Ativo",Funcionarios!$G$2:$G$176,A79,Funcionarios!$M$2:$M$176,$C$6),0) | E79: =IFERROR(AVERAGEIFS(Funcionarios!$P$2:$P$176,Funcionarios!$O$2:$O$176,"Ativo",Funcionarios!$G$2:$G$176,A79,Funcionarios!$M$2:$M$176,$C$6),0) | F79: =IFERROR(AVERAGEIFS(Funcionarios!$N$2:$N$176,Funcionarios!$O$2:$O$176,"Ativo",Funcionarios!$G$2:$G$176,A79,Funcionarios!$M$2:$M$176,$C$6),0) | G79: =COUNTIFS(Funcionarios!$G$2:$G$176,A79,Funcionarios!$M$2:$M$176,$C$6,Funcionarios!$J$2:$J$176,">="&$B$8,Funcionarios!$J$2:$J$176,"<="&$B$9) | H79: =COUNTIFS(Funcionarios!$G$2:$G$176,A79,Funcionarios!$M$2:$M$176,$C$6,Funcionarios!$K$2:$K$176,">="&$B$8,Funcionarios!$K$2:$K$176,"<="&$B$9)
A80: Diretoria | B80: =COUNTIFS(Funcionarios!$O$2:$O$176,"Ativo",Funcionarios!$G$2:$G$176,A80,Funcionarios!$M$2:$M$176,$C$6) | C80: =IFERROR(COUNTIFS(Funcionarios!$O$2:$O$176,"Ativo",Funcionarios!$G$2:$G$176,A80,Funcionarios!$M$2:$M$176,$C$6,Funcionarios!$C$2:$C$176,"F")/B80,0) | D80: =IFERROR(AVERAGEIFS(Funcionarios!$I$2:$I$176,Funcionarios!$O$2:$O$176,"Ativo",Funcionarios!$G$2:$G$176,A80,Funcionarios!$M$2:$M$176,$C$6),0) | E80: =IFERROR(AVERAGEIFS(Funcionarios!$P$2:$P$176,Funcionarios!$O$2:$O$176,"Ativo",Funcionarios!$G$2:$G$176,A80,Funcionarios!$M$2:$M$176,$C$6),0) | F80: =IFERROR(AVERAGEIFS(Funcionarios!$N$2:$N$176,Funcionarios!$O$2:$O$176,"Ativo",Funcionarios!$G$2:$G$176,A80,Funcionarios!$M$2:$M$176,$C$6),0) | G80: =COUNTIFS(Funcionarios!$G$2:$G$176,A80,Funcionarios!$M$2:$M$176,$C$6,Funcionarios!$J$2:$J$176,">="&$B$8,Funcionarios!$J$2:$J$176,"<="&$B$9) | H80: =COUNTIFS(Funcionarios!$G$2:$G$176,A80,Funcionarios!$M$2:$M$176,$C$6,Funcionarios!$K$2:$K$176,">="&$B$8,Funcionarios!$K$2:$K$176,"<="&$B$9)

Sheet Funcionarios
A1: Matrícula | B1: Nome | C1: Gênero | D1: Nascimento | E1: Idade | F1: Faixa etária | G1: Departamento | H1: Nível | I1: Salário | J1: Admissão | K1: Desligamento | L1: Motivo | M1: Unidade | N1: Avaliação | O1: Status | P1: Tempo de casa (anos) | Q1: Liderança
A2: M1001 | B2: Beatriz Costa | C2: F | D2: 35553 | E2: =DATEDIF(D2,IF(K2="",Calc!$B$7,K2),"y") | F2: =LOOKUP(E2,{0,25,35,45,55},{"18-24","25-34","35-44","45-54","55+"}) | G2: Comercial | H2: Assistente | I2: 2800 | J2: 45034 | M2: Recife | N2: 3.2 | O2: =IF(K2="","Ativo","Desligado") | P2: =ROUND((IF(K2="",Calc!$B$7,K2)-J2)/365.25,1) | Q2: =IF(OR(H2="Coordenação",H2="Gerência",H2="Diretoria"),"Sim","Não")
A3: M1002 | B3: Vinícius Ribeiro | C3: M | D3: 34002 | E3: =DATEDIF(D3,IF(K3="",Calc!$B$7,K3),"y") | F3: =LOOKUP(E3,{0,25,35,45,55},{"18-24","25-34","35-44","45-54","55+"}) | G3: Financeiro | H3: Assistente | I3: 4500 | J3: 43771 | M3: Recife | N3: 3.8 | O3: =IF(K3="","Ativo","Desligado") | P3: =ROUND((IF(K3="",Calc!$B$7,K3)-J3)/365.25,1) | Q3: =IF(OR(H3="Coordenação",H3="Gerência",H3="Diretoria"),"Sim","Não")
A4: M1003 | B4: Henrique Fernandes | C4: M | D4: 35888 | E4: =DATEDIF(D4,IF(K4="",Calc!$B$7,K4),"y") | F4: =LOOKUP(E4,{0,25,35,45,55},{"18-24","25-34","35-44","45-54","55+"}) | G4: Comercial | H4: Assistente | I4: 3500 | J4: 43174 | M4: Recife | N4: 3.7 | O4: =IF(K4="","Ativo","Desligado") | P4: =ROUND((IF(K4="",Calc!$B$7,K4)-J4)/365.25,1) | Q4: =IF(OR(H4="Coordenação",H4="Gerência",H4="Diretoria"),"Sim","Não")
A5: M1004 | B5: Daniela Barbosa | C5: F | D5: 31211 | E5: =DATEDIF(D5,IF(K5="",Calc!$B$7,K5),"y") | F5: =LOOKUP(E5,{0,25,35,45,55},{"18-24","25-34","35-44","45-54","55+"}) | G5: Comercial | H5: Analista | I5: 4150 | J5: 41026 | M5: São Paulo | N5: 4.5 | O5: =IF(K5="","Ativo","Desligado") | P5: =ROUND((IF(K5="",Calc!$B$7,K5)-J5)/365.25,1) | Q5: =IF(OR(H5="Coordenação",H5="Gerência",H5="Diretoria"),"Sim","Não")
A6: M1005 | B6: Mariana Fernandes | C6: F | D6: 25799 | E6: =DATEDIF(D6,IF(K6="",Calc!$B$7,K6),"y") | F6: =LOOKUP(E6,{0,25,35,45,55},{"18-24","25-34","35-44","45-54","55+"}) | G6: Comercial | H6: Assistente | I6: 3600 | J6: 45459 | M6: São Paulo | N6: 2.7 | O6: =IF(K6="","Ativo","Desligado") | P6: =ROUND((IF(K6="",Calc!$B$7,K6)-J6)/365.25,1) | Q6: =IF(OR(H6="Coordenação",H6="Gerência",H6="Diretoria"),"Sim","Não")
A7: M1006 | B7: Carolina Vieira | C7: F | D7: 36857 | E7: =DATEDIF(D7,IF(K7="",Calc!$B$7,K7),"y") | F7: =LOOKUP(E7,{0,25,35,45,55},{"18-24","25-34","35-44","45-54","55+"}) | G7: Tecnologia | H7: Coordenação | I7: 15800 | J7: 44738 | M7: Belo Horizonte | N7: 3.5 | O7: =IF(K7="","Ativo","Desligado") | P7: =ROUND((IF(K7="",Calc!$B$7,K7)-J7)/365.25,1) | Q7: =IF(OR(H7="Coordenação",H7="Gerência",H7="Diretoria"),"Sim","Não")
A8: M1007 | B8: Sofia Rodrigues | C8: F | D8: 29434 | E8: =DATEDIF(D8,IF(K8="",Calc!$B$7,K8),"y") | F8: =LOOKUP(E8,{0,25,35,45,55},{"18-24","25-34","35-44","45-54","55+"}) | G8: Comercial | H8: Assistente | I8: 3350 | J8: 43993 | M8: São Paulo | N8: 3.3 | O8: =IF(K8="","Ativo","Desligado") | P8: =ROUND((IF(K8="",Calc!$B$7,K8)-J8)/365.25,1) | Q8: =IF(OR(H8="Coordenação",H8="Gerência",H8="Diretoria"),"Sim","Não")
A9: M1008 | B9: Eduardo Ribeiro | C9: M | D9: 24848 | E9: =DATEDIF(D9,IF(K9="",Calc!$B$7,K9),"y") | F9: =LOOKUP(E9,{0,25,35,45,55},{"18-24","25-34","35-44","45-54","55+"}) | G9: RH | H9: Especialista | I9: 7050 | J9: 43987 | K9: 45989 | L9: Dispensa | M9: Recife | N9: 2.3 | O9: =IF(K9="","Ativo","Desligado") | P9: =ROUND((IF(K9="",Calc!$B$7,K9)-J9)/365.25,1) | Q9: =IF(OR(H9="Coordenação",H9="Gerência",H9="Diretoria"),"Sim","Não")
A10: M1009 | B10: Marcelo Vieira | C10: M | D10: 37481 | E10: =DATEDIF(D10,IF(K10="",Calc!$B$7,K10),"y") | F10: =LOOKUP(E10,{0,25,35,45,55},{"18-24","25-34","35-44","45-54","55+"}) | G10: Financeiro | H10: Analista | I10: 6350 | J10: 44640 | M10: Curitiba | N10: 3.5 | O10: =IF(K10="","Ativo","Desligado") | P10: =ROUND((IF(K10="",Calc!$B$7,K10)-J10)/365.25,1) | Q10: =IF(OR(H10="Coordenação",H10="Gerência",H10="Diretoria"),"Sim","Não")
A11: M1010 | B11: Beatriz Barbosa | C11: F | D11: 27782 | E11: =DATEDIF(D11,IF(K11="",Calc!$B$7,K11),"y") | F11: =LOOKUP(E11,{0,25,35,45,55},{"18-24","25-34","35-44","45-54","55+"}) | G11: Financeiro | H11: Analista | I11: 6050 | J11: 44174 | K11: 45958 | L11: Pedido de demissão | M11: São Paulo | N11: 3.6 | O11: =IF(K11="","Ativo","Desligado") | P11: =ROUND((IF(K11="",Calc!$B$7,K11)-J11)/365.25,1) | Q11: =IF(OR(H11="Coordenação",H11="Gerência",H11="Diretoria"),"Sim","Não")
A12: M1011 | B12: Thiago Carvalho | C12: M | D12: 35876 | E12: =DATEDIF(D12,IF(K12="",Calc!$B$7,K12),"y") | F12: =LOOKUP(E12,{0,25,35,45,55},{"18-24","25-34","35-44","45-54","55+"}) | G12: Comercial | H12: Assistente | I12: 3250 | J12: 41646 | M12: Recife | N12: 3.9 | O12: =IF(K12="","Ativo","Desligado") | P12: =ROUND((IF(K12="",Calc!$B$7,K12)-J12)/365.25,1) | Q12: =IF(OR(H12="Coordenação",H12="Gerência",H12="Diretoria"),"Sim","Não")
A13: M1012 | B13: Patrícia Ribeiro | C13: F | D13: 34548 | E13: =DATEDIF(D13,IF(K13="",Calc!$B$7,K13),"y") | F13: =LOOKUP(E13,{0,25,35,45,55},{"18-24","25-34","35-44","45-54","55+"}) | G13: Comercial | H13: Assistente | I13: 2800 | J13: 44775 | M13: São Paulo | N13: 3.4 | O13: =IF(K13="","Ativo","Desligado") | P13: =ROUND((IF(K13="",Calc!$B$7,K13)-J13)/365.25,1) | Q13: =IF(OR(H13="Coordenação",H13="Gerência",H13="Diretoria"),"Sim","Não")
A14: M1013 | B14: Leonardo Pereira | C14: M | D14: 28526 | E14: =DATEDIF(D14,IF(K14="",Calc!$B$7,K14),"y") | F14: =LOOKUP(E14,{0,25,35,45,55},{"18-24","25-34","35-44","45-54","55+"}) | G14: Comercial | H14: Gerência | I14: 11250 | J14: 42983 | M14: São Paulo | N14: 4.5 | O14: =IF(K14="","Ativo","Desligado") | P14: =ROUND((IF(K14="",Calc!$B$7,K14)-J14)/365.25,1) | Q14: =IF(OR(H14="Coordenação",H14="Gerência",H14="Diretoria"),"Sim","Não")
A15: M1014 | B15: Thiago Ferreira | C15: M | D15: 27198 | E15: =DATEDIF(D15,IF(K15="",Calc!$B$7,K15),"y") | F15: =LOOKUP(E15,{0,25,35,45,55},{"18-24","25-34","35-44","45-54","55+"}) | G15: Marketing | H15: Assistente | I15: 4400 | J15: 41179 | M15: Recife | N15: 4.1 | O15: =IF(K15="","Ativo","Desligado") | P15: =ROUND((IF(K15="",Calc!$B$7,K15)-J15)/365.25,1) | Q15: =IF(OR(H15="Coordenação",H15="Gerência",H15="Diretoria"),"Sim","Não")
A16: M1015 | B16: Tatiane Nunes | C16: F | D16: 29580 | E16: =DATEDIF(D16,IF(K16="",Calc!$B$7,K16),"y") | F16: =LOOKUP(E16,{0,25,35,45,55},{"18-24","25-34","35-44","45-54","55+"}) | G16: Financeiro | H16: Analista | I16: 5550 | J16: 41382 | M16: Curitiba | N16: 3.9 | O16: =IF(K16="","Ativo","Desligado") | P16: =ROUND((IF(K16="",Calc!$B$7,K16)-J16)/365.25,1) | Q16: =IF(OR(H16="Coordenação",H16="Gerência",H16="Diretoria"),"Sim","Não")
A17: M1016 | B17: Henrique Vieira | C17: M | D17: 30043 | E17: =DATEDIF(D17,IF(K17="",Calc!$B$7,K17),"y") | F17: =LOOKUP(E17,{0,25,35,45,55},{"18-24","25-34","35-44","45-54","55+"}) | G17: Financeiro | H17: Coordenação | I17: 9850 | J17: 41930 | M17: Curitiba | N17: 3 | O17: =IF(K17="","Ativo","Desligado") | P17: =ROUND((IF(K17="",Calc!$B$7,K17)-J17)/365.25,1) | Q17: =IF(OR(H17="Coordenação",H17="Gerência",H17="Diretoria"),"Sim","Não")
A18: M1017 | B18: Camila Martins | C18: F | D18: 29034 | E18: =DATEDIF(D18,IF(K18="",Calc!$B$7,K18),"y") | F18: =LOOKUP(E18,{0,25,35,45,55},{"18-24","25-34","35-44","45-54","55+"}) | G18: Tecnologia | H18: Gerência | I18: 22200 | J18: 44452 | M18: São Paulo | N18: 4 | O18: =IF(K18="","Ativo","Desligado") | P18: =ROUND((IF(K18="",Calc!$B$7,K18)-J18)/365.25,1) | Q18: =IF(OR(H18="Coordenação",H18="Gerência",H18="Diretoria"),"Sim","Não")
A19: M1018 | B19: Leonardo Moreira | C19: M | D19: 37310 | E19: =DATEDIF(D19,IF(K19="",Calc!$B$7,K19),"y") | F19: =LOOKUP(E19,{0,25,35,45,55},{"18-24","25-34","35-44","45-54","55+"}) | G19: Financeiro | H19: Assistente | I19: 4700 | J19: 43252 | M19: Belo Horizonte | N19: 3.7 | O19: =IF(K19="","Ativo","Desligado") | P19: =ROUND((IF(K19="",Calc!$B$7,K19)-J19)/365.25,1) | Q19: =IF(OR(H19="Coordenação",H19="Gerência",H19="Diretoria"),"Sim","Não")
A20: M1019 | B20: Patrícia Vieira | C20: F | D20: 31371 | E20: =DATEDIF(D20,IF(K20="",Calc!$B$7,K20),"y") | F20: =LOOKUP(E20,{0,25,35,45,55},{"18-24","25-34","35-44","45-54","55+"}) | G20: Operações | H20: Analista | I20: 3250 | J20: 41398 | K20: 46199 | L20: Pedido de demissão | M20: São Paulo | N20: 3.1 | O20: =IF(K20="","Ativo","Desligado") | P20: =ROUND((IF(K20="",Calc!$B$7,K20)-J20)/365.25,1) | Q20: =IF(OR(H20="Coordenação",H20="Gerência",H20="Diretoria"),"Sim","Não")
A21: M1020 | B21: Rafael Barbosa | C21: M | D21: 28852 | E21: =DATEDIF(D21,IF(K21="",Calc!$B$7,K21),"y") | F21: =LOOKUP(E21,{0,25,35,45,55},{"18-24","25-34","35-44","45-54","55+"}) | G21: Marketing | H21: Coordenação | I21: 10400 | J21: 43237 | M21: São Paulo | N21: 3.2 | O21: =IF(K21="","Ativo","Desligado") | P21: =ROUND((IF(K21="",Calc!$B$7,K21)-J21)/365.25,1) | Q21: =IF(OR(H21="Coordenação",H21="Gerência",H21="Diretoria"),"Sim","Não")
A22: M1021 | B22: Samuel Vieira | C22: M | D22: 31123 | E22: =DATEDIF(D22,IF(K22="",Calc!$B$7,K22),"y") | F22: =LOOKUP(E22,{0,25,35,45,55},{"18-24","25-34","35-44","45-54","55+"}) | G22: Financeiro | H22: Especialista | I22: 7600 | J22: 41634 | M22: Recife | N22: 3.8 | O22: =IF(K22="","Ativo","Desligado") | P22: =ROUND((IF(K22="",Calc!$B$7,K22)-J22)/365.25,1) | Q22: =IF(OR(H22="Coordenação",H22="Gerência",H22="Diretoria"),"Sim","Não")
A23: M1022 | B23: Igor Gomes | C23: M | D23: 28302 | E23: =DATEDIF(D23,IF(K23="",Calc!$B$7,K23),"y") | F23: =LOOKUP(E23,{0,25,35,45,55},{"18-24","25-34","35-44","45-54","55+"}) | G23: Operações | H23: Analista | I23: 3400 | J23: 45578 | M23: São Paulo | N23: 3.8 | O23: =IF(K23="","Ativo","Desligado") | P23: =ROUND((IF(K23="",Calc!$B$7,K23)-J23)/365.25,1) | Q23: =IF(OR(H23="Coordenação",H23="Gerência",H23="Diretoria"),"Sim","Não")
A24: M1023 | B24: Leonardo Lopes | C24: M | D24: 36261 | E24: =DATEDIF(D24,IF(K24="",Calc!$B$7,K24),"y") | F24: =LOOKUP(E24,{0,25,35,45,55},{"18-24","25-34","35-44","45-54","55+"}) | G24: Tecnologia | H24: Analista | I24: 8250 | J24: 41399 | K24: 45969 | L24: Pedido de demissão | M24: Curitiba | N24: 4.3 | O24: =IF(K24="","Ativo","Desligado") | P24: =ROUND((IF(K24="",Calc!$B$7,K24)-J24)/365.25,1) | Q24: =IF(OR(H24="Coordenação",H24="Gerência",H24="Diretoria"),"Sim","Não")
A25: M1024 | B25: Gabriela Pereira | C25: F | D25: 35009 | E25: =DATEDIF(D25,IF(K25="",Calc!$B$7,K25),"y") | F25: =LOOKUP(E25,{0,25,35,45,55},{"18-24","25-34","35-44","45-54","55+"}) | G25: Tecnologia | H25: Coordenação | I25: 14650 | J25: 45239 | K25: 46111 | L25: Pedido de demissão | M25: São Paulo | N25: 5 | O25: =IF(K25="","Ativo","Desligado") | P25: =ROUND((IF(K25="",Calc!$B$7,K25)-J25)/365.25,1) | Q25: =IF(OR(H25="Coordenação",H25="Gerência",H25="Diretoria"),"Sim","Não")
A26: M1025 | B26: Carlos Oliveira | C26: M | D26: 35017 | E26: =DATEDIF(D26,IF(K26="",Calc!$B$7,K26),"y") | F26: =LOOKUP(E26,{0,25,35,45,55},{"18-24","25-34","35-44","45-54","55+"}) | G26: RH | H26: Especialista | I26: 8000 | J26: 42716 | M26: São Paulo | N26: 3.4 | O26: =IF(K26="","Ativo","Desligado") | P26: =ROUND((IF(K26="",Calc!$B$7,K26)-J26)/365.25,1) | Q26: =IF(OR(H26="Coordenação",H26="Gerência",H26="Diretoria"),"Sim","Não")
A27: M1026 | B27: Felipe Lopes | C27: M | D27: 33073 | E27: =DATEDIF(D27,IF(K27="",Calc!$B$7,K27),"y") | F27: =LOOKUP(E27,{0,25,35,45,55},{"18-24","25-34","35-44","45-54","55+"}) | G27: Financeiro | H27: Especialista | I27: 8200 | J27: 41311 | M27: São Paulo | N27: 3.5 | O27: =IF(K27="","Ativo","Desligado") | P27: =ROUND((IF(K27="",Calc!$B$7,K27)-J27)/365.25,1) | Q27: =IF(OR(H27="Coordenação",H27="Gerência",H27="Diretoria"),"Sim","Não")
A28: M1027 | B28: Natália Alves | C28: F | D28: 29544 | E28: =DATEDIF(D28,IF(K28="",Calc!$B$7,K28),"y") | F28: =LOOKUP(E28,{0,25,35,45,55},{"18-24","25-34","35-44","45-54","55+"}) | G28: Tecnologia | H28: Assistente | I28: 6600 | J28: 45503 | M28: São Paulo | N28: 4.6 | O28: =IF(K28="","Ativo","Desligado") | P28: =ROUND((IF(K28="",Calc!$B$7,K28)-J28)/365.25,1) | Q28: =IF(OR(H28="Coordenação",H28="Gerência",H28="Diretoria"),"Sim","Não")
A29: M1028 | B29: Bruno Almeida | C29: M | D29: 35659 | E29: =DATEDIF(D29,IF(K29="",Calc!$B$7,K29),"y") | F29: =LOOKUP(E29,{0,25,35,45,55},{"18-24","25-34","35-44","45-54","55+"}) | G29: Comercial | H29: Assistente | I29: 3050 | J29: 45262 | K29: 45658 | L29: Dispensa | M29: Curitiba | N29: 4.4 | O29: =IF(K29="","Ativo","Desligado") | P29: =ROUND((IF(K29="",Calc!$B$7,K29)-J29)/365.25,1) | Q29: =IF(OR(H29="Coordenação",H29="Gerência",H29="Diretoria"),"Sim","Não")
A30: M1029 | B30: Larissa Pereira | C30: F | D30: 34044 | E30: =DATEDIF(D30,IF(K30="",Calc!$B$7,K30),"y") | F30: =LOOKUP(E30,{0,25,35,45,55},{"18-24","25-34","35-44","45-54","55+"}) | G30: Operações | H30: Analista | I30: 3300 | J30: 42435 | M30: Belo Horizonte | N30: 5 | O30: =IF(K30="","Ativo","Desligado") | P30: =ROUND((IF(K30="",Calc!$B$7,K30)-J30)/365.25,1) | Q30: =IF(OR(H30="Coordenação",H30="Gerência",H30="Diretoria"),"Sim","Não")
A31: M1030 | B31: Henrique Silva | C31: M | D31: 30970 | E31: =DATEDIF(D31,IF(K31="",Calc!$B$7,K31),"y") | F31: =LOOKUP(E31,{0,25,35,45,55},{"18-24","25-34","35-44","45-54","55+"}) | G31: Operações | H31: Assistente | I31: 2250 | J31: 42962 | K31: 46246 | L31: Pedido de demissão | M31: São Paulo | N31: 4.3 | O31: =IF(K31="","Ativo","Desligado") | P31: =ROUND((IF(K31="",Calc!$B$7,K31)-J31)/365.25,1) | Q31: =IF(OR(H31="Coordenação",H31="Gerência",H31="Diretoria"),"Sim","Não")
A32: M1031 | B32: Gabriela Moreira | C32: F | D32: 30019 | E32: =DATEDIF(D32,IF(K32="",Calc!$B$7,K32),"y") | F32: =LOOKUP(E32,{0,25,35,45,55},{"18-24","25-34","35-44","45-54","55+"}) | G32: Operações | H32: Assistente | I32: 2550 | J32: 41239 | M32: São Paulo | N32: 3.4 | O32: =IF(K32="","Ativo","Desligado") | P32: =ROUND((IF(K32="",Calc!$B$7,K32)-J32)/365.25,1) | Q32: =IF(OR(H32="Coordenação",H32="Gerência",H32="Diretoria"),"Sim","Não")
A33: M1032 | B33: Patrícia Nunes | C33: F | D33: 27293 | E33: =DATEDIF(D33,IF(K33="",Calc!$B$7,K33),"y") | F33: =LOOKUP(E33,{0,25,35,45,55},{"18-24","25-34","35-44","45-54","55+"}) | G33: Marketing | H33: Assistente | I33: 4000 | J33: 45590 | M33: São Paulo | N33: 3.9 | O33: =IF(K33="","Ativo","Desligado") | P33: =ROUND((IF(K33="",Calc!$B$7,K33)-J33)/365.25,1) | Q33: =IF(OR(H33="Coordenação",H33="Gerência",H33="Diretoria"),"Sim","Não")
A34: M1033 | B34: João Souza | C34: M | D34: 24209 | E34: =DATEDIF(D34,IF(K34="",Calc!$B$7,K34),"y") | F34: =LOOKUP(E34,{0,25,35,45,55},{"18-24","25-34","35-44","45-54","55+"}) | G34: Financeiro | H34: Analista | I34: 5300 | J34: 42387 | M34: Curitiba | N34: 3.3 | O34: =IF(K34="","Ativo","Desligado") | P34: =ROUND((IF(K34="",Calc!$B$7,K34)-J34)/365.25,1) | Q34: =IF(OR(H34="Coordenação",H34="Gerência",H34="Diretoria"),"Sim","Não")
A35: M1034 | B35: Felipe Nunes | C35: M | D35: 28267 | E35: =DATEDIF(D35,IF(K35="",Calc!$B$7,K35),"y") | F35: =LOOKUP(E35,{0,25,35,45,55},{"18-24","25-34","35-44","45-54","55+"}) | G35: Operações | H35: Analista | I35: 3400 | J35: 41511 | K35: 45677 | L35: Dispensa | M35: Recife | N35: 3.2 | O35: =IF(K35="","Ativo","Desligado") | P35: =ROUND((IF(K35="",Calc!$B$7,K35)-J35)/365.25,1) | Q35: =IF(OR(H35="Coordenação",H35="Gerência",H35="Diretoria"),"Sim","Não")
A36: M1035 | B36: Gabriela Nunes | C36: F | D36: 37327 | E36: =DATEDIF(D36,IF(K36="",Calc!$B$7,K36),"y") | F36: =LOOKUP(E36,{0,25,35,45,55},{"18-24","25-34","35-44","45-54","55+"}) | G36: Operações | H36: Analista | I36: 3550 | J36: 43832 | M36: Curitiba | N36: 4 | O36: =IF(K36="","Ativo","Desligado") | P36: =ROUND((IF(K36="",Calc!$B$7,K36)-J36)/365.25,1) | Q36: =IF(OR(H36="Coordenação",H36="Gerência",H36="Diretoria"),"Sim","Não")
A37: M1036 | B37: Fernanda Nunes | C37: F | D37: 35727 | E37: =DATEDIF(D37,IF(K37="",Calc!$B$7,K37),"y") | F37: =LOOKUP(E37,{0,25,35,45,55},{"18-24","25-34","35-44","45-54","55+"}) | G37: Comercial | H37: Analista | I37: 4450 | J37: 41619 | M37: São Paulo | N37: 3.7 | O37: =IF(K37="","Ativo","Desligado") | P37: =ROUND((IF(K37="",Calc!$B$7,K37)-J37)/365.25,1) | Q37: =IF(OR(H37="Coordenação",H37="Gerência",H37="Diretoria"),"Sim","Não")
A38: M1037 | B38: Mariana Rodrigues | C38: F | D38: 32260 | E38: =DATEDIF(D38,IF(K38="",Calc!$B$7,K38),"y") | F38: =LOOKUP(E38,{0,25,35,45,55},{"18-24","25-34","35-44","45-54","55+"}) | G38: Comercial | H38: Analista | I38: 4650 | J38: 42805 | M38: Curitiba | N38: 4.2 | O38: =IF(K38="","Ativo","Desligado") | P38: =ROUND((IF(K38="",Calc!$B$7,K38)-J38)/365.25,1) | Q38: =IF(OR(H38="Coordenação",H38="Gerência",H38="Diretoria"),"Sim","Não")
A39: M1038 | B39: Gabriela Almeida | C39: F | D39: 27933 | E39: =DATEDIF(D39,IF(K39="",Calc!$B$7,K39),"y") | F39: =LOOKUP(E39,{0,25,35,45,55},{"18-24","25-34","35-44","45-54","55+"}) | G39: Comercial | H39: Analista | I39: 4050 | J39: 42386 | M39: São Paulo | N39: 3.2 | O39: =IF(K39="","Ativo","Desligado") | P39: =ROUND((IF(K39="",Calc!$B$7,K39)-J39)/365.25,1) | Q39: =IF(OR(H39="Coordenação",H39="Gerência",H39="Diretoria"),"Sim","Não")
A40: M1039 | B40: Leonardo Costa | C40: M | D40: 32621 | E40: =DATEDIF(D40,IF(K40="",Calc!$B$7,K40),"y") | F40: =LOOKUP(E40,{0,25,35,45,55},{"18-24","25-34","35-44","45-54","55+"}) | G40: Marketing | H40: Assistente | I40: 4250 | J40: 41463 | M40: Curitiba | N40: 3.7 | O40: =IF(K40="","Ativo","Desligado") | P40: =ROUND((IF(K40="",Calc!$B$7,K40)-J40)/365.25,1) | Q40: =IF(OR(H40="Coordenação",H40="Gerência",H40="Diretoria"),"Sim","Não")
A41: M1040 | B41: Carlos Carvalho | C41: M | D41: 29074 | E41: =DATEDIF(D41,IF(K41="",Calc!$B$7,K41),"y") | F41: =LOOKUP(E41,{0,25,35,45,55},{"18-24","25-34","35-44","45-54","55+"}) | G41: Comercial | H41: Analista | I41: 4550 | J41: 43435 | M41: Recife | N41: 3.8 | O41: =IF(K41="","Ativo","Desligado") | P41: =ROUND((IF(K41="",Calc!$B$7,K41)-J41)/365.25,1) | Q41: =IF(OR(H41="Coordenação",H41="Gerência",H41="Diretoria"),"Sim","Não")
A42: M1041 | B42: Pedro Nunes | C42: M | D42: 33579 | E42: =DATEDIF(D42,IF(K42="",Calc!$B$7,K42),"y") | F42: =LOOKUP(E42,{0,25,35,45,55},{"18-24","25-34","35-44","45-54","55+"}) | G42: Comercial | H42: Gerência | I42: 13400 | J42: 43070 | K42: 45752 | L42: Aposentadoria | M42: Belo Horizonte | N42: 4.4 | O42: =IF(K42="","Ativo","Desligado") | P42: =ROUND((IF(K42="",Calc!$B$7,K42)-J42)/365.25,1) | Q42: =IF(OR(H42="Coordenação",H42="Gerência",H42="Diretoria"),"Sim","Não")
A43: M1042 | B43: Bianca Rocha | C43: F | D43: 26203 | E43: =DATEDIF(D43,IF(K43="",Calc!$B$7,K43),"y") | F43: =LOOKUP(E43,{0,25,35,45,55},{"18-24","25-34","35-44","45-54","55+"}) | G43: Comercial | H43: Especialista | I43: 6950 | J43: 45413 | M43: Recife | N43: 4.5 | O43: =IF(K43="","Ativo","Desligado") | P43: =ROUND((IF(K43="",Calc!$B$7,K43)-J43)/365.25,1) | Q43: =IF(OR(H43="Coordenação",H43="Gerência",H43="Diretoria"),"Sim","Não")
A44: M1043 | B44: Bruno Barbosa | C44: M | D44: 38413 | E44: =DATEDIF(D44,IF(K44="",Calc!$B$7,K44),"y") | F44: =LOOKUP(E44,{0,25,35,45,55},{"18-24","25-34","35-44","45-54","55+"}) | G44: Financeiro | H44: Assistente | I44: 4400 | J44: 43221 | M44: Belo Horizonte | N44: 4.1 | O44: =IF(K44="","Ativo","Desligado") | P44: =ROUND((IF(K44="",Calc!$B$7,K44)-J44)/365.25,1) | Q44: =IF(OR(H44="Coordenação",H44="Gerência",H44="Diretoria"),"Sim","Não")
A45: M1044 | B45: Vinícius Lima | C45: M | D45: 34532 | E45: =DATEDIF(D45,IF(K45="",Calc!$B$7,K45),"y") | F45: =LOOKUP(E45,{0,25,35,45,55},{"18-24","25-34","35-44","45-54","55+"}) | G45: Comercial | H45: Analista | I45: 4350 | J45: 43868 | M45: Recife | N45: 3.4 | O45: =IF(K45="","Ativo","Desligado") | P45: =ROUND((IF(K45="",Calc!$B$7,K45)-J45)/365.25,1) | Q45: =IF(OR(H45="Coordenação",H45="Gerência",H45="Diretoria"),"Sim","Não")
A46: M1045 | B46: Rodrigo Nunes | C46: M | D46: 26067 | E46: =DATEDIF(D46,IF(K46="",Calc!$B$7,K46),"y") | F46: =LOOKUP(E46,{0,25,35,45,55},{"18-24","25-34","35-44","45-54","55+"}) | G46: Operações | H46: Assistente | I46: 2800 | J46: 41703 | M46: Curitiba | N46: 3.8 | O46: =IF(K46="","Ativo","Desligado") | P46: =ROUND((IF(K46="",Calc!$B$7,K46)-J46)/365.25,1) | Q46: =IF(OR(H46="Coordenação",H46="Gerência",H46="Diretoria"),"Sim","Não")
A47: M1046 | B47: Rafael Gomes | C47: M | D47: 33136 | E47: =DATEDIF(D47,IF(K47="",Calc!$B$7,K47),"y") | F47: =LOOKUP(E47,{0,25,35,45,55},{"18-24","25-34","35-44","45-54","55+"}) | G47: Tecnologia | H47: Assistente | I47: 5450 | J47: 41971 | K47: 45783 | L47: Pedido de demissão | M47: Belo Horizonte | N47: 4.7 | O47: =IF(K47="","Ativo","Desligado") | P47: =ROUND((IF(K47="",Calc!$B$7,K47)-J47)/365.25,1) | Q47: =IF(OR(H47="Coordenação",H47="Gerência",H47="Diretoria"),"Sim","Não")
A48: M1047 | B48: Diego Ribeiro | C48: M | D48: 33133 | E48: =DATEDIF(D48,IF(K48="",Calc!$B$7,K48),"y") | F48: =LOOKUP(E48,{0,25,35,45,55},{"18-24","25-34","35-44","45-54","55+"}) | G48: Financeiro | H48: Analista | I48: 5300 | J48: 41621 | M48: São Paulo | N48: 4 | O48: =IF(K48="","Ativo","Desligado") | P48: =ROUND((IF(K48="",Calc!$B$7,K48)-J48)/365.25,1) | Q48: =IF(OR(H48="Coordenação",H48="Gerência",H48="Diretoria"),"Sim","Não")
A49: M1048 | B49: Diego Ferreira | C49: M | D49: 30760 | E49: =DATEDIF(D49,IF(K49="",Calc!$B$7,K49),"y") | F49: =LOOKUP(E49,{0,25,35,45,55},{"18-24","25-34","35-44","45-54","55+"}) | G49: Tecnologia | H49: Gerência | I49: 24450 | J49: 41411 | M49: São Paulo | N49: 4.4 | O49: =IF(K49="","Ativo","Desligado") | P49: =ROUND((IF(K49="",Calc!$B$7,K49)-J49)/365.25,1) | Q49: =IF(OR(H49="Coordenação",H49="Gerência",H49="Diretoria"),"Sim","Não")
A50: M1049 | B50: Luana Lima | C50: F | D50: 28852 | E50: =DATEDIF(D50,IF(K50="",Calc!$B$7,K50),"y") | F50: =LOOKUP(E50,{0,25,35,45,55},{"18-24","25-34","35-44","45-54","55+"}) | G50: Tecnologia | H50: Assistente | I50: 6250 | J50: 44062 | K50: 45827 | L50: Pedido de demissão | M50: Belo Horizonte | N50: 4 | O50: =IF(K50="","Ativo","Desligado") | P50: =ROUND((IF(K50="",Calc!$B$7,K50)-J50)/365.25,1) | Q50: =IF(OR(H50="Coordenação",H50="Gerência",H50="Diretoria"),"Sim","Não")
A51: M1050 | B51: Ana Carvalho | C51: F | D51: 27365 | E51: =DATEDIF(D51,IF(K51="",Calc!$B$7,K51),"y") | F51: =LOOKUP(E51,{0,25,35,45,55},{"18-24","25-34","35-44","45-54","55+"}) | G51: Operações | H51: Coordenação | I51: 6400 | J51: 43117 | M51: São Paulo | N51: 3.6 | O51: =IF(K51="","Ativo","Desligado") | P51: =ROUND((IF(K51="",Calc!$B$7,K51)-J51)/365.25,1) | Q51: =IF(OR(H51="Coordenação",H51="Gerência",H51="Diretoria"),"Sim","Não")
A52: M1051 | B52: Otávio Dias | C52: M | D52: 37389 | E52: =DATEDIF(D52,IF(K52="",Calc!$B$7,K52),"y") | F52: =LOOKUP(E52,{0,25,35,45,55},{"18-24","25-34","35-44","45-54","55+"}) | G52: Comercial | H52: Analista | I52: 4400 | J52: 43702 | M52: São Paulo | N52: 4.1 | O52: =IF(K52="","Ativo","Desligado") | P52: =ROUND((IF(K52="",Calc!$B$7,K52)-J52)/365.25,1) | Q52: =IF(OR(H52="Coordenação",H52="Gerência",H52="Diretoria"),"Sim","Não")
A53: M1052 | B53: Bruno Nunes | C53: M | D53: 33140 | E53: =DATEDIF(D53,IF(K53="",Calc!$B$7,K53),"y") | F53: =LOOKUP(E53,{0,25,35,45,55},{"18-24","25-34","35-44","45-54","55+"}) | G53: RH | H53: Especialista | I53: 7350 | J53: 44444 | M53: Belo Horizonte | N53: 3.8 | O53: =IF(K53="","Ativo","Desligado") | P53: =ROUND((IF(K53="",Calc!$B$7,K53)-J53)/365.25,1) | Q53: =IF(OR(H53="Coordenação",H53="Gerência",H53="Diretoria"),"Sim","Não")
A54: M1053 | B54: Mateus Ferreira | C54: M | D54: 31530 | E54: =DATEDIF(D54,IF(K54="",Calc!$B$7,K54),"y") | F54: =LOOKUP(E54,{0,25,35,45,55},{"18-24","25-34","35-44","45-54","55+"}) | G54: Comercial | H54: Assistente | I54: 2900 | J54: 42519 | K54: 45926 | L54: Pedido de demissão | M54: São Paulo | N54: 3.5 | O54: =IF(K54="","Ativo","Desligado") | P54: =ROUND((IF(K54="",Calc!$B$7,K54)-J54)/365.25,1) | Q54: =IF(OR(H54="Coordenação",H54="Gerência",H54="Diretoria"),"Sim","Não")
A55: M1054 | B55: Eduarda Costa | C55: F | D55: 26635 | E55: =DATEDIF(D55,IF(K55="",Calc!$B$7,K55),"y") | F55: =LOOKUP(E55,{0,25,35,45,55},{"18-24","25-34","35-44","45-54","55+"}) | G55: Operações | H55: Coordenação | I55: 6100 | J55: 43068 | M55: São Paulo | N55: 4.5 | O55: =IF(K55="","Ativo","Desligado") | P55: =ROUND((IF(K55="",Calc!$B$7,K55)-J55)/365.25,1) | Q55: =IF(OR(H55="Coordenação",H55="Gerência",H55="Diretoria"),"Sim","Não")
A56: M1055 | B56: Bruno Pereira | C56: M | D56: 31881 | E56: =DATEDIF(D56,IF(K56="",Calc!$B$7,K56),"y") | F56: =LOOKUP(E56,{0,25,35,45,55},{"18-24","25-34","35-44","45-54","55+"}) | G56: Comercial | H56: Gerência | I56: 12950 | J56: 44740 | M56: Curitiba | N56: 3.5 | O56: =IF(K56="","Ativo","Desligado") | P56: =ROUND((IF(K56="",Calc!$B$7,K56)-J56)/365.25,1) | Q56: =IF(OR(H56="Coordenação",H56="Gerência",H56="Diretoria"),"Sim","Não")
A57: M1056 | B57: Samuel Lima | C57: M | D57: 37242 | E57: =DATEDIF(D57,IF(K57="",Calc!$B$7,K57),"y") | F57: =LOOKUP(E57,{0,25,35,45,55},{"18-24","25-34","35-44","45-54","55+"}) | G57: Financeiro | H57: Analista | I57: 5200 | J57: 45057 | M57: São Paulo | N57: 3.7 | O57: =IF(K57="","Ativo","Desligado") | P57: =ROUND((IF(K57="",Calc!$B$7,K57)-J57)/365.25,1) | Q57: =IF(OR(H57="Coordenação",H57="Gerência",H57="Diretoria"),"Sim","Não")
A58: M1057 | B58: Lucas Oliveira | C58: M | D58: 33698 | E58: =DATEDIF(D58,IF(K58="",Calc!$B$7,K58),"y") | F58: =LOOKUP(E58,{0,25,35,45,55},{"18-24","25-34","35-44","45-54","55+"}) | G58: Financeiro | H58: Assistente | I58: 4650 | J58: 43007 | M58: São Paulo | N58: 4.4 | O58: =IF(K58="","Ativo","Desligado") | P58: =ROUND((IF(K58="",Calc!$B$7,K58)-J58)/365.25,1) | Q58: =IF(OR(H58="Coordenação",H58="Gerência",H58="Diretoria"),"Sim","Não")
A59: M1058 | B59: Thiago Alves | C59: M | D59: 34344 | E59: =DATEDIF(D59,IF(K59="",Calc!$B$7,K59),"y") | F59: =LOOKUP(E59,{0,25,35,45,55},{"18-24","25-34","35-44","45-54","55+"}) | G59: Operações | H59: Analista | I59: 2900 | J59: 44587 | M59: São Paulo | N59: 4.1 | O59: =IF(K59="","Ativo","Desligado") | P59: =ROUND((IF(K59="",Calc!$B$7,K59)-J59)/365.25,1) | Q59: =IF(OR(H59="Coordenação",H59="Gerência",H59="Diretoria"),"Sim","Não")
A60: M1059 | B60: Bruno Silva | C60: M | D60: 36580 | E60: =DATEDIF(D60,IF(K60="",Calc!$B$7,K60),"y") | F60: =LOOKUP(E60,{0,25,35,45,55},{"18-24","25-34","35-44","45-54","55+"}) | G60: Tecnologia | H60: Assistente | I60: 6050 | J60: 45011 | M60: São Paulo | N60: 4.2 | O60: =IF(K60="","Ativo","Desligado") | P60: =ROUND((IF(K60="",Calc!$B$7,K60)-J60)/365.25,1) | Q60: =IF(OR(H60="Coordenação",H60="Gerência",H60="Diretoria"),"Sim","Não")
A61: M1060 | B61: Otávio Nunes | C61: M | D61: 28202 | E61: =DATEDIF(D61,IF(K61="",Calc!$B$7,K61),"y") | F61: =LOOKUP(E61,{0,25,35,45,55},{"18-24","25-34","35-44","45-54","55+"}) | G61: Operações | H61: Gerência | I61: 8800 | J61: 43552 | M61: Recife | N61: 3.7 | O61: =IF(K61="","Ativo","Desligado") | P61: =ROUND((IF(K61="",Calc!$B$7,K61)-J61)/365.25,1) | Q61: =IF(OR(H61="Coordenação",H61="Gerência",H61="Diretoria"),"Sim","Não")
A62: M1061 | B62: Camila Gomes | C62: F | D62: 33657 | E62: =DATEDIF(D62,IF(K62="",Calc!$B$7,K62),"y") | F62: =LOOKUP(E62,{0,25,35,45,55},{"18-24","25-34","35-44","45-54","55+"}) | G62: Operações | H62: Assistente | I62: 2250 | J62: 43056 | M62: Curitiba | N62: 4.4 | O62: =IF(K62="","Ativo","Desligado") | P62: =ROUND((IF(K62="",Calc!$B$7,K62)-J62)/365.25,1) | Q62: =IF(OR(H62="Coordenação",H62="Gerência",H62="Diretoria"),"Sim","Não")
A63: M1062 | B63: Vinícius Lima | C63: M | D63: 34885 | E63: =DATEDIF(D63,IF(K63="",Calc!$B$7,K63),"y") | F63: =LOOKUP(E63,{0,25,35,45,55},{"18-24","25-34","35-44","45-54","55+"}) | G63: RH | H63: Coordenação | I63: 8250 | J63: 41346 | M63: Belo Horizonte | N63: 3.5 | O63: =IF(K63="","Ativo","Desligado") | P63: =ROUND((IF(K63="",Calc!$B$7,K63)-J63)/365.25,1) | Q63: =IF(OR(H63="Coordenação",H63="Gerência",H63="Diretoria"),"Sim","Não")
A64: M1063 | B64: Eduardo Pereira | C64: M | D64: 36668 | E64: =DATEDIF(D64,IF(K64="",Calc!$B$7,K64),"y") | F64: =LOOKUP(E64,{0,25,35,45,55},{"18-24","25-34","35-44","45-54","55+"}) | G64: Comercial | H64: Assistente | I64: 2850 | J64: 43567 | M64: São Paulo | N64: 3.8 | O64: =IF(K64="","Ativo","Desligado") | P64: =ROUND((IF(K64="",Calc!$B$7,K64)-J64)/365.25,1) | Q64: =IF(OR(H64="Coordenação",H64="Gerência",H64="Diretoria"),"Sim","Não")
A65: M1064 | B65: Pedro Gomes | C65: M | D65: 29054 | E65: =DATEDIF(D65,IF(K65="",Calc!$B$7,K65),"y") | F65: =LOOKUP(E65,{0,25,35,45,55},{"18-24","25-34","35-44","45-54","55+"}) | G65: Comercial | H65: Coordenação | I65: 8550 | J65: 44512 | M65: Curitiba | N65: 3.6 | O65: =IF(K65="","Ativo","Desligado") | P65: =ROUND((IF(K65="",Calc!$B$7,K65)-J65)/365.25,1) | Q65: =IF(OR(H65="Coordenação",H65="Gerência",H65="Diretoria"),"Sim","Não")
A66: M1065 | B66: Fernanda Santos | C66: F | D66: 37966 | E66: =DATEDIF(D66,IF(K66="",Calc!$B$7,K66),"y") | F66: =LOOKUP(E66,{0,25,35,45,55},{"18-24","25-34","35-44","45-54","55+"}) | G66: Comercial | H66: Assistente | I66: 3600 | J66: 43636 | K66: 45975 | L66: Dispensa | M66: São Paulo | N66: 3.1 | O66: =IF(K66="","Ativo","Desligado") | P66: =ROUND((IF(K66="",Calc!$B$7,K66)-J66)/365.25,1) | Q66: =IF(OR(H66="Coordenação",H66="Gerência",H66="Diretoria"),"Sim","Não")
A67: M1066 | B67: Nicolas Almeida | C67: M | D67: 34492 | E67: =DATEDIF(D67,IF(K67="",Calc!$B$7,K67),"y") | F67: =LOOKUP(E67,{0,25,35,45,55},{"18-24","25-34","35-44","45-54","55+"}) | G67: Operações | H67: Assistente | I67: 2550 | J67: 43175 | M67: Belo Horizonte | N67: 3.9 | O67: =IF(K67="","Ativo","Desligado") | P67: =ROUND((IF(K67="",Calc!$B$7,K67)-J67)/365.25,1) | Q67: =IF(OR(H67="Coordenação",H67="Gerência",H67="Diretoria"),"Sim","Não")
A68: M1067 | B68: Gustavo Pereira | C68: M | D68: 28806 | E68: =DATEDIF(D68,IF(K68="",Calc!$B$7,K68),"y") | F68: =LOOKUP(E68,{0,25,35,45,55},{"18-24","25-34","35-44","45-54","55+"}) | G68: Comercial | H68: Assistente | I68: 3300 | J68: 43541 | K68: 45884 | L68: Fim de contrato | M68: São Paulo | N68: 4.8 | O68: =IF(K68="","Ativo","Desligado") | P68: =ROUND((IF(K68="",Calc!$B$7,K68)-J68)/365.25,1) | Q68: =IF(OR(H68="Coordenação",H68="Gerência",H68="Diretoria"),"Sim","Não")
A69: M1068 | B69: Bruno Almeida | C69: M | D69: 29500 | E69: =DATEDIF(D69,IF(K69="",Calc!$B$7,K69),"y") | F69: =LOOKUP(E69,{0,25,35,45,55},{"18-24","25-34","35-44","45-54","55+"}) | G69: Comercial | H69: Assistente | I69: 3350 | J69: 41499 | M69: Curitiba | N69: 3.9 | O69: =IF(K69="","Ativo","Desligado") | P69: =ROUND((IF(K69="",Calc!$B$7,K69)-J69)/365.25,1) | Q69: =IF(OR(H69="Coordenação",H69="Gerência",H69="Diretoria"),"Sim","Não")
A70: M1069 | B70: Mariana Souza | C70: F | D70: 29055 | E70: =DATEDIF(D70,IF(K70="",Calc!$B$7,K70),"y") | F70: =LOOKUP(E70,{0,25,35,45,55},{"18-24","25-34","35-44","45-54","55+"}) | G70: Comercial | H70: Especialista | I70: 6700 | J70: 42665 | M70: Curitiba | N70: 4.2 | O70: =IF(K70="","Ativo","Desligado") | P70: =ROUND((IF(K70="",Calc!$B$7,K70)-J70)/365.25,1) | Q70: =IF(OR(H70="Coordenação",H70="Gerência",H70="Diretoria"),"Sim","Não")
A71: M1070 | B71: Vanessa Santos | C71: F | D71: 33091 | E71: =DATEDIF(D71,IF(K71="",Calc!$B$7,K71),"y") | F71: =LOOKUP(E71,{0,25,35,45,55},{"18-24","25-34","35-44","45-54","55+"}) | G71: Comercial | H71: Gerência | I71: 12750 | J71: 42382 | K71: 45724 | L71: Dispensa | M71: São Paulo | N71: 3 | O71: =IF(K71="","Ativo","Desligado") | P71: =ROUND((IF(K71="",Calc!$B$7,K71)-J71)/365.25,1) | Q71: =IF(OR(H71="Coordenação",H71="Gerência",H71="Diretoria"),"Sim","Não")
A72: M1071 | B72: Patrícia Pereira | C72: F | D72: 35157 | E72: =DATEDIF(D72,IF(K72="",Calc!$B$7,K72),"y") | F72: =LOOKUP(E72,{0,25,35,45,55},{"18-24","25-34","35-44","45-54","55+"}) | G72: RH | H72: Especialista | I72: 7200 | J72: 41428 | M72: Belo Horizonte | N72: 3.5 | O72: =IF(K72="","Ativo","Desligado") | P72: =ROUND((IF(K72="",Calc!$B$7,K72)-J72)/365.25,1) | Q72: =IF(OR(H72="Coordenação",H72="Gerência",H72="Diretoria"),"Sim","Não")
A73: M1072 | B73: Otávio Ribeiro | C73: M | D73: 36084 | E73: =DATEDIF(D73,IF(K73="",Calc!$B$7,K73),"y") | F73: =LOOKUP(E73,{0,25,35,45,55},{"18-24","25-34","35-44","45-54","55+"}) | G73: Operações | H73: Coordenação | I73: 6700 | J73: 45434 | M73: São Paulo | N73: 2.9 | O73: =IF(K73="","Ativo","Desligado") | P73: =ROUND((IF(K73="",Calc!$B$7,K73)-J73)/365.25,1) | Q73: =IF(OR(H73="Coordenação",H73="Gerência",H73="Diretoria"),"Sim","Não")
A74: M1073 | B74: Felipe Dias | C74: M | D74: 26314 | E74: =DATEDIF(D74,IF(K74="",Calc!$B$7,K74),"y") | F74: =LOOKUP(E74,{0,25,35,45,55},{"18-24","25-34","35-44","45-54","55+"}) | G74: Marketing | H74: Analista | I74: 4600 | J74: 43943 | M74: Curitiba | N74: 5 | O74: =IF(K74="","Ativo","Desligado") | P74: =ROUND((IF(K74="",Calc!$B$7,K74)-J74)/365.25,1) | Q74: =IF(OR(H74="Coordenação",H74="Gerência",H74="Diretoria"),"Sim","Não")
A75: M1074 | B75: Patrícia Soares | C75: F | D75: 29268 | E75: =DATEDIF(D75,IF(K75="",Calc!$B$7,K75),"y") | F75: =LOOKUP(E75,{0,25,35,45,55},{"18-24","25-34","35-44","45-54","55+"}) | G75: Comercial | H75: Analista | I75: 4050 | J75: 43888 | K75: 46190 | L75: Pedido de demissão | M75: São Paulo | N75: 3.8 | O75: =IF(K75="","Ativo","Desligado") | P75: =ROUND((IF(K75="",Calc!$B$7,K75)-J75)/365.25,1) | Q75: =IF(OR(H75="Coordenação",H75="Gerência",H75="Diretoria"),"Sim","Não")
A76: M1075 | B76: Isabela Gomes | C76: F | D76: 35993 | E76: =DATEDIF(D76,IF(K76="",Calc!$B$7,K76),"y") | F76: =LOOKUP(E76,{0,25,35,45,55},{"18-24","25-34","35-44","45-54","55+"}) | G76: Operações | H76: Assistente | I76: 2400 | J76: 43128 | M76: Curitiba | N76: 2.8 | O76: =IF(K76="","Ativo","Desligado") | P76: =ROUND((IF(K76="",Calc!$B$7,K76)-J76)/365.25,1) | Q76: =IF(OR(H76="Coordenação",H76="Gerência",H76="Diretoria"),"Sim","Não")
A77: M1076 | B77: Mariana Rocha | C77: F | D77: 27462 | E77: =DATEDIF(D77,IF(K77="",Calc!$B$7,K77),"y") | F77: =LOOKUP(E77,{0,25,35,45,55},{"18-24","25-34","35-44","45-54","55+"}) | G77: Tecnologia | H77: Assistente | I77: 5450 | J77: 41191 | M77: São Paulo | N77: 4.9 | O77: =IF(K77="","Ativo","Desligado") | P77: =ROUND((IF(K77="",Calc!$B$7,K77)-J77)/365.25,1) | Q77: =IF(OR(H77="Coordenação",H77="Gerência",H77="Diretoria"),"Sim","Não")
A78: M1077 | B78: Patrícia Nunes | C78: F | D78: 36976 | E78: =DATEDIF(D78,IF(K78="",Calc!$B$7,K78),"y") | F78: =LOOKUP(E78,{0,25,35,45,55},{"18-24","25-34","35-44","45-54","55+"}) | G78: Operações | H78: Analista | I78: 3150 | J78: 43112 | M78: Recife | N78: 3.9 | O78: =IF(K78="","Ativo","Desligado") | P78: =ROUND((IF(K78="",Calc!$B$7,K78)-J78)/365.25,1) | Q78: =IF(OR(H78="Coordenação",H78="Gerência",H78="Diretoria"),"Sim","Não")
A79: M1078 | B79: Leonardo Almeida | C79: M | D79: 28492 | E79: =DATEDIF(D79,IF(K79="",Calc!$B$7,K79),"y") | F79: =LOOKUP(E79,{0,25,35,45,55},{"18-24","25-34","35-44","45-54","55+"}) | G79: Tecnologia | H79: Analista | I79: 8950 | J79: 44024 | M79: São Paulo | N79: 4.7 | O79: =IF(K79="","Ativo","Desligado") | P79: =ROUND((IF(K79="",Calc!$B$7,K79)-J79)/365.25,1) | Q79: =IF(OR(H79="Coordenação",H79="Gerência",H79="Diretoria"),"Sim","Não")
A80: M1079 | B80: Rafael Ribeiro | C80: M | D80: 37261 | E80: =DATEDIF(D80,IF(K80="",Calc!$B$7,K80),"y") | F80: =LOOKUP(E80,{0,25,35,45,55},{"18-24","25-34","35-44","45-54","55+"}) | G80: Operações | H80: Especialista | I80: 4400 | J80: 43217 | M80: São Paulo | N80: 3.9 | O80: =IF(K80="","Ativo","Desligado") | P80: =ROUND((IF(K80="",Calc!$B$7,K80)-J80)/365.25,1) | Q80: =IF(OR(H80="Coordenação",H80="Gerência",H80="Diretoria"),"Sim","Não")
A81: M1080 | B81: Isabela Lima | C81: F | D81: 38098 | E81: =DATEDIF(D81,IF(K81="",Calc!$B$7,K81),"y") | F81: =LOOKUP(E81,{0,25,35,45,55},{"18-24","25-34","35-44","45-54","55+"}) | G81: Comercial | H81: Assistente | I81: 3350 | J81: 42567 | K81: 45737 | L81: Dispensa | M81: Belo Horizonte | N81: 4.4 | O81: =IF(K81="","Ativo","Desligado") | P81: =ROUND((IF(K81="",Calc!$B$7,K81)-J81)/365.25,1) | Q81: =IF(OR(H81="Coordenação",H81="Gerência",H81="Diretoria"),"Sim","Não")
A82: M1081 | B82: Vinícius Ferreira | C82: M | D82: 31840 | E82: =DATEDIF(D82,IF(K82="",Calc!$B$7,K82),"y") | F82: =LOOKUP(E82,{0,25,35,45,55},{"18-24","25-34","35-44","45-54","55+"}) | G82: Tecnologia | H82: Analista | I82: 8200 | J82: 43751 | M82: Belo Horizonte | N82: 3.4 | O82: =IF(K82="","Ativo","Desligado") | P82: =ROUND((IF(K82="",Calc!$B$7,K82)-J82)/365.25,1) | Q82: =IF(OR(H82="Coordenação",H82="Gerência",H82="Diretoria"),"Sim","Não")
A83: M1082 | B83: Henrique Silva | C83: M | D83: 33486 | E83: =DATEDIF(D83,IF(K83="",Calc!$B$7,K83),"y") | F83: =LOOKUP(E83,{0,25,35,45,55},{"18-24","25-34","35-44","45-54","55+"}) | G83: Tecnologia | H83: Analista | I83: 7100 | J83: 41222 | M83: Curitiba | N83: 2.9 | O83: =IF(K83="","Ativo","Desligado") | P83: =ROUND((IF(K83="",Calc!$B$7,K83)-J83)/365.25,1) | Q83: =IF(OR(H83="Coordenação",H83="Gerência",H83="Diretoria"),"Sim","Não")
A84: M1083 | B84: Carolina Rodrigues | C84: F | D84: 31824 | E84: =DATEDIF(D84,IF(K84="",Calc!$B$7,K84),"y") | F84: =LOOKUP(E84,{0,25,35,45,55},{"18-24","25-34","35-44","45-54","55+"}) | G84: RH | H84: Analista | I84: 5500 | J84: 41642 | M84: São Paulo | N84: 4.6 | O84: =IF(K84="","Ativo","Desligado") | P84: =ROUND((IF(K84="",Calc!$B$7,K84)-J84)/365.25,1) | Q84: =IF(OR(H84="Coordenação",H84="Gerência",H84="Diretoria"),"Sim","Não")
A85: M1084 | B85: Yasmin Alves | C85: F | D85: 31811 | E85: =DATEDIF(D85,IF(K85="",Calc!$B$7,K85),"y") | F85: =LOOKUP(E85,{0,25,35,45,55},{"18-24","25-34","35-44","45-54","55+"}) | G85: Comercial | H85: Analista | I85: 3700 | J85: 43061 | M85: Belo Horizonte | N85: 4.7 | O85: =IF(K85="","Ativo","Desligado") | P85: =ROUND((IF(K85="",Calc!$B$7,K85)-J85)/365.25,1) | Q85: =IF(OR(H85="Coordenação",H85="Gerência",H85="Diretoria"),"Sim","Não")
A86: M1085 | B86: Isabela Costa | C86: F | D86: 35243 | E86: =DATEDIF(D86,IF(K86="",Calc!$B$7,K86),"y") | F86: =LOOKUP(E86,{0,25,35,45,55},{"18-24","25-34","35-44","45-54","55+"}) | G86: Comercial | H86: Assistente | I86: 3050 | J86: 44703 | K86: 45663 | L86: Pedido de demissão | M86: São Paulo | N86: 2.9 | O86: =IF(K86="","Ativo","Desligado") | P86: =ROUND((IF(K86="",Calc!$B$7,K86)-J86)/365.25,1) | Q86: =IF(OR(H86="Coordenação",H86="Gerência",H86="Diretoria"),"Sim","Não")
A87: M1086 | B87: Marcelo Ribeiro | C87: M | D87: 30845 | E87: =DATEDIF(D87,IF(K87="",Calc!$B$7,K87),"y") | F87: =LOOKUP(E87,{0,25,35,45,55},{"18-24","25-34","35-44","45-54","55+"}) | G87: Marketing | H87: Gerência | I87: 16250 | J87: 43197 | M87: Belo Horizonte | N87: 4 | O87: =IF(K87="","Ativo","Desligado") | P87: =ROUND((IF(K87="",Calc!$B$7,K87)-J87)/365.25,1) | Q87: =IF(OR(H87="Coordenação",H87="Gerência",H87="Diretoria"),"Sim","Não")
A88: M1087 | B88: Natália Rodrigues | C88: F | D88: 34536 | E88: =DATEDIF(D88,IF(K88="",Calc!$B$7,K88),"y") | F88: =LOOKUP(E88,{0,25,35,45,55},{"18-24","25-34","35-44","45-54","55+"}) | G88: Comercial | H88: Assistente | I88: 3450 | J88: 45558 | K88: 45990 | L88: Pedido de demissão | M88: São Paulo | N88: 4.5 | O88: =IF(K88="","Ativo","Desligado") | P88: =ROUND((IF(K88="",Calc!$B$7,K88)-J88)/365.25,1) | Q88: =IF(OR(H88="Coordenação",H88="Gerência",H88="Diretoria"),"Sim","Não")
A89: M1088 | B89: Diego Dias | C89: M | D89: 27141 | E89: =DATEDIF(D89,IF(K89="",Calc!$B$7,K89),"y") | F89: =LOOKUP(E89,{0,25,35,45,55},{"18-24","25-34","35-44","45-54","55+"}) | G89: Operações | H89: Analista | I89: 3550 | J89: 40936 | M89: São Paulo | N89: 4.8 | O89: =IF(K89="","Ativo","Desligado") | P89: =ROUND((IF(K89="",Calc!$B$7,K89)-J89)/365.25,1) | Q89: =IF(OR(H89="Coordenação",H89="Gerência",H89="Diretoria"),"Sim","Não")
A90: M1089 | B90: Carolina Santos | C90: F | D90: 32160 | E90: =DATEDIF(D90,IF(K90="",Calc!$B$7,K90),"y") | F90: =LOOKUP(E90,{0,25,35,45,55},{"18-24","25-34","35-44","45-54","55+"}) | G90: Tecnologia | H90: Analista | I90: 8800 | J90: 43423 | M90: Recife | N90: 3.8 | O90: =IF(K90="","Ativo","Desligado") | P90: =ROUND((IF(K90="",Calc!$B$7,K90)-J90)/365.25,1) | Q90: =IF(OR(H90="Coordenação",H90="Gerência",H90="Diretoria"),"Sim","Não")
A91: M1090 | B91: Pedro Barbosa | C91: M | D91: 34377 | E91: =DATEDIF(D91,IF(K91="",Calc!$B$7,K91),"y") | F91: =LOOKUP(E91,{0,25,35,45,55},{"18-24","25-34","35-44","45-54","55+"}) | G91: Marketing | H91: Assistente | I91: 3900 | J91: 41711 | M91: São Paulo | N91: 3.5 | O91: =IF(K91="","Ativo","Desligado") | P91: =ROUND((IF(K91="",Calc!$B$7,K91)-J91)/365.25,1) | Q91: =IF(OR(H91="Coordenação",H91="Gerência",H91="Diretoria"),"Sim","Não")
A92: M1091 | B92: Rafael Barbosa | C92: M | D92: 33403 | E92: =DATEDIF(D92,IF(K92="",Calc!$B$7,K92),"y") | F92: =LOOKUP(E92,{0,25,35,45,55},{"18-24","25-34","35-44","45-54","55+"}) | G92: Comercial | H92: Analista | I92: 4050 | J92: 41083 | M92: Belo Horizonte | N92: 5 | O92: =IF(K92="","Ativo","Desligado") | P92: =ROUND((IF(K92="",Calc!$B$7,K92)-J92)/365.25,1) | Q92: =IF(OR(H92="Coordenação",H92="Gerência",H92="Diretoria"),"Sim","Não")
A93: M1092 | B93: Lucas Ribeiro | C93: M | D93: 36387 | E93: =DATEDIF(D93,IF(K93="",Calc!$B$7,K93),"y") | F93: =LOOKUP(E93,{0,25,35,45,55},{"18-24","25-34","35-44","45-54","55+"}) | G93: Comercial | H93: Analista | I93: 4600 | J93: 43717 | K93: 45862 | L93: Dispensa | M93: São Paulo | N93: 4.1 | O93: =IF(K93="","Ativo","Desligado") | P93: =ROUND((IF(K93="",Calc!$B$7,K93)-J93)/365.25,1) | Q93: =IF(OR(H93="Coordenação",H93="Gerência",H93="Diretoria"),"Sim","Não")
A94: M1093 | B94: Samuel Almeida | C94: M | D94: 26013 | E94: =DATEDIF(D94,IF(K94="",Calc!$B$7,K94),"y") | F94: =LOOKUP(E94,{0,25,35,45,55},{"18-24","25-34","35-44","45-54","55+"}) | G94: Comercial | H94: Especialista | I94: 6950 | J94: 45280 | M94: Belo Horizonte | N94: 3.1 | O94: =IF(K94="","Ativo","Desligado") | P94: =ROUND((IF(K94="",Calc!$B$7,K94)-J94)/365.25,1) | Q94: =IF(OR(H94="Coordenação",H94="Gerência",H94="Diretoria"),"Sim","Não")
A95: M1094 | B95: Yasmin Carvalho | C95: F | D95: 30317 | E95: =DATEDIF(D95,IF(K95="",Calc!$B$7,K95),"y") | F95: =LOOKUP(E95,{0,25,35,45,55},{"18-24","25-34","35-44","45-54","55+"}) | G95: Operações | H95: Analista | I95: 3150 | J95: 42503 | M95: São Paulo | N95: 4.7 | O95: =IF(K95="","Ativo","Desligado") | P95: =ROUND((IF(K95="",Calc!$B$7,K95)-J95)/365.25,1) | Q95: =IF(OR(H95="Coordenação",H95="Gerência",H95="Diretoria"),"Sim","Não")
A96: M1095 | B96: Beatriz Fernandes | C96: F | D96: 28238 | E96: =DATEDIF(D96,IF(K96="",Calc!$B$7,K96),"y") | F96: =LOOKUP(E96,{0,25,35,45,55},{"18-24","25-34","35-44","45-54","55+"}) | G96: Financeiro | H96: Especialista | I96: 7900 | J96: 42095 | K96: 46232 | L96: Pedido de demissão | M96: São Paulo | N96: 4.3 | O96: =IF(K96="","Ativo","Desligado") | P96: =ROUND((IF(K96="",Calc!$B$7,K96)-J96)/365.25,1) | Q96: =IF(OR(H96="Coordenação",H96="Gerência",H96="Diretoria"),"Sim","Não")
A97: M1096 | B97: Carlos Santos | C97: M | D97: 32139 | E97: =DATEDIF(D97,IF(K97="",Calc!$B$7,K97),"y") | F97: =LOOKUP(E97,{0,25,35,45,55},{"18-24","25-34","35-44","45-54","55+"}) | G97: RH | H97: Assistente | I97: 3200 | J97: 43645 | K97: 45730 | L97: Pedido de demissão | M97: Belo Horizonte | N97: 3.4 | O97: =IF(K97="","Ativo","Desligado") | P97: =ROUND((IF(K97="",Calc!$B$7,K97)-J97)/365.25,1) | Q97: =IF(OR(H97="Coordenação",H97="Gerência",H97="Diretoria"),"Sim","Não")
A98: M1097 | B98: Otávio Dias | C98: M | D98: 38676 | E98: =DATEDIF(D98,IF(K98="",Calc!$B$7,K98),"y") | F98: =LOOKUP(E98,{0,25,35,45,55},{"18-24","25-34","35-44","45-54","55+"}) | G98: Operações | H98: Coordenação | I98: 6650 | J98: 45163 | M98: Recife | N98: 3.7 | O98: =IF(K98="","Ativo","Desligado") | P98: =ROUND((IF(K98="",Calc!$B$7,K98)-J98)/365.25,1) | Q98: =IF(OR(H98="Coordenação",H98="Gerência",H98="Diretoria"),"Sim","Não")
A99: M1098 | B99: Larissa Rocha | C99: F | D99: 32016 | E99: =DATEDIF(D99,IF(K99="",Calc!$B$7,K99),"y") | F99: =LOOKUP(E99,{0,25,35,45,55},{"18-24","25-34","35-44","45-54","55+"}) | G99: Operações | H99: Coordenação | I99: 5650 | J99: 43147 | K99: 46088 | L99: Pedido de demissão | M99: São Paulo | N99: 2.5 | O99: =IF(K99="","Ativo","Desligado") | P99: =ROUND((IF(K99="",Calc!$B$7,K99)-J99)/365.25,1) | Q99: =IF(OR(H99="Coordenação",H99="Gerência",H99="Diretoria"),"Sim","Não")
A100: M1099 | B100: Gustavo Soares | C100: M | D100: 36378 | E100: =DATEDIF(D100,IF(K100="",Calc!$B$7,K100),"y") | F100: =LOOKUP(E100,{0,25,35,45,55},{"18-24","25-34","35-44","45-54","55+"}) | G100: Tecnologia | H100: Analista | I100: 7250 | J100: 43671 | M100: São Paulo | N100: 4.6 | O100: =IF(K100="","Ativo","Desligado") | P100: =ROUND((IF(K100="",Calc!$B$7,K100)-J100)/365.25,1) | Q100: =IF(OR(H100="Coordenação",H100="Gerência",H100="Diretoria"),"Sim","Não")
...
